<anim ver="netanim-3.109" filetype="animation" >
<node id="0" sysId="0" locX="5" locY="15" />
<node id="1" sysId="0" locX="10" locY="2" />
<node id="2" sysId="0" locX="15" locY="15" />
<nu p="c" t="0" id="0" r="255" g="0" b="0" />
<nu p="c" t="0" id="1" r="255" g="0" b="0" />
<nu p="c" t="0" id="2" r="255" g="0" b="0" />
<link fromId="0" toId="1" fd="10.1.1.1~00:00:00:00:00:01" td="10.1.1.2~00:00:00:00:00:02" ld="" />
<nonp2plinkproperties id="0" ipAddress="127.0.0.1~00:00:00:00:00:00" channelType="Unknown channel" />
<link fromId="1" toId="2" fd="10.1.2.1~00:00:00:00:00:03" td="10.1.2.2~00:00:00:00:00:04" ld="" />
<link fromId="1" toId="2" fd="10.1.3.1~00:00:00:00:00:05" td="10.1.3.2~00:00:00:00:00:06" ld="" />
<nonp2plinkproperties id="1" ipAddress="127.0.0.1~00:00:00:00:00:00" channelType="Unknown channel" />
<nonp2plinkproperties id="2" ipAddress="127.0.0.1~00:00:00:00:00:00" channelType="Unknown channel" />
<ip n="0" >
<address >10.1.1.1</address>

<address >127.0.0.1</address>

</ip>
<ip n="0" >
<address >10.1.1.1</address>

<address >127.0.0.1</address>

</ip>
<ip n="1" >
<address >10.1.1.2</address>

<address >10.1.2.1</address>

<address >10.1.3.1</address>

<address >127.0.0.1</address>

</ip>
<ip n="1" >
<address >10.1.1.2</address>

<address >10.1.2.1</address>

<address >10.1.3.1</address>

<address >127.0.0.1</address>

</ip>
<ip n="1" >
<address >10.1.1.2</address>

<address >10.1.2.1</address>

<address >10.1.3.1</address>

<address >127.0.0.1</address>

</ip>
<ip n="1" >
<address >10.1.1.2</address>

<address >10.1.2.1</address>

<address >10.1.3.1</address>

<address >127.0.0.1</address>

</ip>
<ip n="2" >
<address >10.1.2.2</address>

<address >10.1.3.2</address>

<address >127.0.0.1</address>

</ip>
<ip n="2" >
<address >10.1.2.2</address>

<address >10.1.3.2</address>

<address >127.0.0.1</address>

</ip>
<ip n="2" >
<address >10.1.2.2</address>

<address >10.1.3.2</address>

<address >127.0.0.1</address>

</ip>
<ipv6 n="0" >
<address >::1</address>

</ipv6>
<ipv6 n="1" >
<address >::1</address>

</ipv6>
<ipv6 n="2" >
<address >::1</address>

</ipv6>
<nu p="s" t="0" id="0" w="1" h="1" />
<nu p="s" t="0" id="1" w="1" h="1" />
<nu p="s" t="0" id="2" w="1" h="1" />
<ncs ncId="0" n="RemainingEnergy" t="DOUBLE" />
<nu p="d" t="0" id="0" descr="Studio
10.1.1.1
(Video+Data Src)" />
<nu p="d" t="0" id="1" descr="Router
10.1.1.2 | 10.1.2.1
(PBR Point)" />
<nu p="d" t="0" id="2" descr="Cloud
10.1.2.2
(Render Farm)" />
<nu p="c" t="0" id="0" r="0" g="255" b="0" />
<nu p="c" t="0" id="1" r="255" g="255" b="0" />
<nu p="c" t="0" id="2" r="0" g="0" b="255" />
<p fId="0" fbTx="2.02" lbTx="2.020336" tId="1" fbRx="2.022" lbRx="2.022336" />
<p fId="1" fbTx="2.022336" lbTx="2.024016" tId="2" fbRx="2.027336" lbRx="2.029016" />
<p fId="0" fbTx="2.04" lbTx="2.040336" tId="1" fbRx="2.042" lbRx="2.042336" />
<p fId="1" fbTx="2.042336" lbTx="2.044016" tId="2" fbRx="2.047336" lbRx="2.049016" />
<p fId="0" fbTx="2.06" lbTx="2.060336" tId="1" fbRx="2.062" lbRx="2.062336" />
<p fId="1" fbTx="2.062336" lbTx="2.064016" tId="2" fbRx="2.067336" lbRx="2.069016" />
<p fId="0" fbTx="2.08" lbTx="2.080336" tId="1" fbRx="2.082" lbRx="2.082336" />
<p fId="1" fbTx="2.082336" lbTx="2.084016" tId="2" fbRx="2.087336" lbRx="2.089016" />
<p fId="0" fbTx="2.1" lbTx="2.100336" tId="1" fbRx="2.102" lbRx="2.102336" />
<p fId="1" fbTx="2.102336" lbTx="2.104016" tId="2" fbRx="2.107336" lbRx="2.109016" />
<p fId="0" fbTx="2.12" lbTx="2.120336" tId="1" fbRx="2.122" lbRx="2.122336" />
<p fId="1" fbTx="2.122336" lbTx="2.124016" tId="2" fbRx="2.127336" lbRx="2.129016" />
<p fId="0" fbTx="2.14" lbTx="2.140336" tId="1" fbRx="2.142" lbRx="2.142336" />
<p fId="1" fbTx="2.142336" lbTx="2.144016" tId="2" fbRx="2.147336" lbRx="2.149016" />
<p fId="0" fbTx="2.16" lbTx="2.160336" tId="1" fbRx="2.162" lbRx="2.162336" />
<p fId="1" fbTx="2.162336" lbTx="2.164016" tId="2" fbRx="2.167336" lbRx="2.169016" />
<p fId="0" fbTx="2.18" lbTx="2.180336" tId="1" fbRx="2.182" lbRx="2.182336" />
<p fId="1" fbTx="2.182336" lbTx="2.184016" tId="2" fbRx="2.187336" lbRx="2.189016" />
<p fId="0" fbTx="2.2" lbTx="2.200336" tId="1" fbRx="2.202" lbRx="2.202336" />
<p fId="1" fbTx="2.202336" lbTx="2.204016" tId="2" fbRx="2.207336" lbRx="2.209016" />
<p fId="0" fbTx="2.22" lbTx="2.220336" tId="1" fbRx="2.222" lbRx="2.222336" />
<p fId="1" fbTx="2.222336" lbTx="2.224016" tId="2" fbRx="2.227336" lbRx="2.229016" />
<p fId="0" fbTx="2.24" lbTx="2.240336" tId="1" fbRx="2.242" lbRx="2.242336" />
<p fId="1" fbTx="2.242336" lbTx="2.244016" tId="2" fbRx="2.247336" lbRx="2.249016" />
<p fId="0" fbTx="2.26" lbTx="2.260336" tId="1" fbRx="2.262" lbRx="2.262336" />
<p fId="1" fbTx="2.262336" lbTx="2.264016" tId="2" fbRx="2.267336" lbRx="2.269016" />
<p fId="0" fbTx="2.28" lbTx="2.280336" tId="1" fbRx="2.282" lbRx="2.282336" />
<p fId="1" fbTx="2.282336" lbTx="2.284016" tId="2" fbRx="2.287336" lbRx="2.289016" />
<p fId="0" fbTx="2.3" lbTx="2.300336" tId="1" fbRx="2.302" lbRx="2.302336" />
<p fId="1" fbTx="2.302336" lbTx="2.304016" tId="2" fbRx="2.307336" lbRx="2.309016" />
<p fId="0" fbTx="2.32" lbTx="2.320336" tId="1" fbRx="2.322" lbRx="2.322336" />
<p fId="1" fbTx="2.322336" lbTx="2.324016" tId="2" fbRx="2.327336" lbRx="2.329016" />
<p fId="0" fbTx="2.34" lbTx="2.340336" tId="1" fbRx="2.342" lbRx="2.342336" />
<p fId="1" fbTx="2.342336" lbTx="2.344016" tId="2" fbRx="2.347336" lbRx="2.349016" />
<p fId="0" fbTx="2.36" lbTx="2.360336" tId="1" fbRx="2.362" lbRx="2.362336" />
<p fId="1" fbTx="2.362336" lbTx="2.364016" tId="2" fbRx="2.367336" lbRx="2.369016" />
<p fId="0" fbTx="2.38" lbTx="2.380336" tId="1" fbRx="2.382" lbRx="2.382336" />
<p fId="1" fbTx="2.382336" lbTx="2.384016" tId="2" fbRx="2.387336" lbRx="2.389016" />
<p fId="0" fbTx="2.4" lbTx="2.400336" tId="1" fbRx="2.402" lbRx="2.402336" />
<p fId="1" fbTx="2.402336" lbTx="2.404016" tId="2" fbRx="2.407336" lbRx="2.409016" />
<p fId="0" fbTx="2.42" lbTx="2.420336" tId="1" fbRx="2.422" lbRx="2.422336" />
<p fId="1" fbTx="2.422336" lbTx="2.424016" tId="2" fbRx="2.427336" lbRx="2.429016" />
<p fId="0" fbTx="2.44" lbTx="2.440336" tId="1" fbRx="2.442" lbRx="2.442336" />
<p fId="1" fbTx="2.442336" lbTx="2.444016" tId="2" fbRx="2.447336" lbRx="2.449016" />
<p fId="0" fbTx="2.46" lbTx="2.460336" tId="1" fbRx="2.462" lbRx="2.462336" />
<p fId="1" fbTx="2.462336" lbTx="2.464016" tId="2" fbRx="2.467336" lbRx="2.469016" />
<p fId="0" fbTx="2.48" lbTx="2.480336" tId="1" fbRx="2.482" lbRx="2.482336" />
<p fId="1" fbTx="2.482336" lbTx="2.484016" tId="2" fbRx="2.487336" lbRx="2.489016" />
<p fId="0" fbTx="2.5" lbTx="2.5000928" tId="1" fbRx="2.502" lbRx="2.5020928" />
<p fId="0" fbTx="2.5000928" lbTx="2.5004288" tId="1" fbRx="2.5020928" lbRx="2.5024288" />
<p fId="1" fbTx="2.5020928" lbTx="2.5021856" tId="2" fbRx="2.5220928" lbRx="2.5221856" />
<p fId="1" fbTx="2.5024288" lbTx="2.5041088" tId="2" fbRx="2.5074288" lbRx="2.5091088" />
<p fId="0" fbTx="2.52" lbTx="2.520336" tId="1" fbRx="2.522" lbRx="2.522336" />
<p fId="2" fbTx="2.5221856" lbTx="2.5226496" tId="1" fbRx="2.5271856" lbRx="2.5276496" />
<p fId="1" fbTx="2.522336" lbTx="2.524016" tId="2" fbRx="2.527336" lbRx="2.529016" />
<p fId="1" fbTx="2.5276496" lbTx="2.5277424" tId="2" fbRx="2.5476496" lbRx="2.5477424" />
<p fId="0" fbTx="2.54" lbTx="2.540336" tId="1" fbRx="2.542" lbRx="2.542336" />
<p fId="1" fbTx="2.542336" lbTx="2.544016" tId="2" fbRx="2.547336" lbRx="2.549016" />
<p fId="2" fbTx="2.5477424" lbTx="2.5482064" tId="1" fbRx="2.5527424" lbRx="2.5532064" />
<p fId="1" fbTx="2.5532064" lbTx="2.5532992" tId="2" fbRx="2.5732064" lbRx="2.5732992" />
<p fId="0" fbTx="2.56" lbTx="2.560336" tId="1" fbRx="2.562" lbRx="2.562336" />
<p fId="1" fbTx="2.562336" lbTx="2.564016" tId="2" fbRx="2.567336" lbRx="2.569016" />
<p fId="2" fbTx="2.5732992" lbTx="2.5737632" tId="1" fbRx="2.5782992" lbRx="2.5787632" />
<p fId="1" fbTx="2.5787632" lbTx="2.578856" tId="2" fbRx="2.5987632" lbRx="2.598856" />
<p fId="0" fbTx="2.58" lbTx="2.580336" tId="1" fbRx="2.582" lbRx="2.582336" />
<p fId="1" fbTx="2.582336" lbTx="2.584016" tId="2" fbRx="2.587336" lbRx="2.589016" />
<p fId="2" fbTx="2.598856" lbTx="2.59932" tId="1" fbRx="2.603856" lbRx="2.60432" />
<p fId="0" fbTx="2.6" lbTx="2.600336" tId="1" fbRx="2.602" lbRx="2.602336" />
<p fId="1" fbTx="2.602336" lbTx="2.604016" tId="2" fbRx="2.607336" lbRx="2.609016" />
<p fId="1" fbTx="2.60432" lbTx="2.6044128" tId="2" fbRx="2.62432" lbRx="2.6244128" />
<p fId="0" fbTx="2.62" lbTx="2.620336" tId="1" fbRx="2.622" lbRx="2.622336" />
<p fId="1" fbTx="2.622336" lbTx="2.624016" tId="2" fbRx="2.627336" lbRx="2.629016" />
<p fId="2" fbTx="2.6244128" lbTx="2.6248768" tId="1" fbRx="2.6294128" lbRx="2.6298768" />
<p fId="1" fbTx="2.6298768" lbTx="2.6299696" tId="2" fbRx="2.6498768" lbRx="2.6499696" />
<p fId="0" fbTx="2.64" lbTx="2.640336" tId="1" fbRx="2.642" lbRx="2.642336" />
<p fId="1" fbTx="2.642336" lbTx="2.644016" tId="2" fbRx="2.647336" lbRx="2.649016" />
<p fId="2" fbTx="2.6499696" lbTx="2.6504336" tId="1" fbRx="2.6549696" lbRx="2.6554336" />
<p fId="1" fbTx="2.6554336" lbTx="2.6555264" tId="2" fbRx="2.6754336" lbRx="2.6755264" />
<p fId="0" fbTx="2.66" lbTx="2.660336" tId="1" fbRx="2.662" lbRx="2.662336" />
<p fId="1" fbTx="2.662336" lbTx="2.664016" tId="2" fbRx="2.667336" lbRx="2.669016" />
<p fId="2" fbTx="2.6755264" lbTx="2.6759904" tId="1" fbRx="2.6805264" lbRx="2.6809904" />
<p fId="0" fbTx="2.68" lbTx="2.680336" tId="1" fbRx="2.682" lbRx="2.682336" />
<p fId="1" fbTx="2.6809904" lbTx="2.6810832" tId="2" fbRx="2.7009904" lbRx="2.7010832" />
<p fId="1" fbTx="2.682336" lbTx="2.684016" tId="2" fbRx="2.687336" lbRx="2.689016" />
<p fId="0" fbTx="2.7" lbTx="2.700336" tId="1" fbRx="2.702" lbRx="2.702336" />
<p fId="2" fbTx="2.7010832" lbTx="2.7015472" tId="1" fbRx="2.7060832" lbRx="2.7065472" />
<p fId="1" fbTx="2.702336" lbTx="2.704016" tId="2" fbRx="2.707336" lbRx="2.709016" />
<p fId="1" fbTx="2.7065472" lbTx="2.70664" tId="2" fbRx="2.7265472" lbRx="2.72664" />
<p fId="0" fbTx="2.72" lbTx="2.720336" tId="1" fbRx="2.722" lbRx="2.722336" />
<p fId="1" fbTx="2.722336" lbTx="2.724016" tId="2" fbRx="2.727336" lbRx="2.729016" />
<p fId="2" fbTx="2.72664" lbTx="2.727104" tId="1" fbRx="2.73164" lbRx="2.732104" />
<p fId="1" fbTx="2.732104" lbTx="2.7321968" tId="2" fbRx="2.752104" lbRx="2.7521968" />
<p fId="0" fbTx="2.74" lbTx="2.740336" tId="1" fbRx="2.742" lbRx="2.742336" />
<p fId="1" fbTx="2.742336" lbTx="2.744016" tId="2" fbRx="2.747336" lbRx="2.749016" />
<p fId="2" fbTx="2.7521968" lbTx="2.7526608" tId="1" fbRx="2.7571968" lbRx="2.7576608" />
<p fId="1" fbTx="2.7576608" lbTx="2.7577536" tId="2" fbRx="2.7776608" lbRx="2.7777536" />
<p fId="0" fbTx="2.76" lbTx="2.760336" tId="1" fbRx="2.762" lbRx="2.762336" />
<p fId="1" fbTx="2.762336" lbTx="2.764016" tId="2" fbRx="2.767336" lbRx="2.769016" />
<p fId="2" fbTx="2.7777536" lbTx="2.7782176" tId="1" fbRx="2.7827536" lbRx="2.7832176" />
<p fId="0" fbTx="2.78" lbTx="2.780336" tId="1" fbRx="2.782" lbRx="2.782336" />
<p fId="1" fbTx="2.782336" lbTx="2.784016" tId="2" fbRx="2.787336" lbRx="2.789016" />
<p fId="1" fbTx="2.7832176" lbTx="2.7833104" tId="2" fbRx="2.8032176" lbRx="2.8033104" />
<p fId="0" fbTx="2.8" lbTx="2.800336" tId="1" fbRx="2.802" lbRx="2.802336" />
<p fId="1" fbTx="2.802336" lbTx="2.804016" tId="2" fbRx="2.807336" lbRx="2.809016" />
<p fId="2" fbTx="2.8033104" lbTx="2.8037744" tId="1" fbRx="2.8083104" lbRx="2.8087744" />
<p fId="1" fbTx="2.8087744" lbTx="2.8088672" tId="2" fbRx="2.8287744" lbRx="2.8288672" />
<p fId="0" fbTx="2.82" lbTx="2.820336" tId="1" fbRx="2.822" lbRx="2.822336" />
<p fId="1" fbTx="2.822336" lbTx="2.824016" tId="2" fbRx="2.827336" lbRx="2.829016" />
<p fId="2" fbTx="2.8288672" lbTx="2.8293312" tId="1" fbRx="2.8338672" lbRx="2.8343312" />
<p fId="1" fbTx="2.8343312" lbTx="2.834424" tId="2" fbRx="2.8543312" lbRx="2.854424" />
<p fId="0" fbTx="2.84" lbTx="2.840336" tId="1" fbRx="2.842" lbRx="2.842336" />
<p fId="1" fbTx="2.842336" lbTx="2.844016" tId="2" fbRx="2.847336" lbRx="2.849016" />
<p fId="2" fbTx="2.854424" lbTx="2.854888" tId="1" fbRx="2.859424" lbRx="2.859888" />
<p fId="1" fbTx="2.859888" lbTx="2.8599808" tId="2" fbRx="2.879888" lbRx="2.8799808" />
<p fId="0" fbTx="2.86" lbTx="2.860336" tId="1" fbRx="2.862" lbRx="2.862336" />
<p fId="1" fbTx="2.862336" lbTx="2.864016" tId="2" fbRx="2.867336" lbRx="2.869016" />
<p fId="2" fbTx="2.8799808" lbTx="2.8804448" tId="1" fbRx="2.8849808" lbRx="2.8854448" />
<p fId="0" fbTx="2.88" lbTx="2.880336" tId="1" fbRx="2.882" lbRx="2.882336" />
<p fId="1" fbTx="2.882336" lbTx="2.884016" tId="2" fbRx="2.887336" lbRx="2.889016" />
<p fId="1" fbTx="2.8854448" lbTx="2.8855376" tId="2" fbRx="2.9054448" lbRx="2.9055376" />
<p fId="0" fbTx="2.9" lbTx="2.900336" tId="1" fbRx="2.902" lbRx="2.902336" />
<p fId="1" fbTx="2.902336" lbTx="2.904016" tId="2" fbRx="2.907336" lbRx="2.909016" />
<p fId="2" fbTx="2.9055376" lbTx="2.9060016" tId="1" fbRx="2.9105376" lbRx="2.9110016" />
<p fId="1" fbTx="2.9110016" lbTx="2.9110944" tId="2" fbRx="2.9310016" lbRx="2.9310944" />
<p fId="0" fbTx="2.92" lbTx="2.920336" tId="1" fbRx="2.922" lbRx="2.922336" />
<p fId="1" fbTx="2.922336" lbTx="2.924016" tId="2" fbRx="2.927336" lbRx="2.929016" />
<p fId="2" fbTx="2.9310944" lbTx="2.9315584" tId="1" fbRx="2.9360944" lbRx="2.9365584" />
<p fId="1" fbTx="2.9365584" lbTx="2.9366512" tId="2" fbRx="2.9565584" lbRx="2.9566512" />
<p fId="0" fbTx="2.94" lbTx="2.940336" tId="1" fbRx="2.942" lbRx="2.942336" />
<p fId="1" fbTx="2.942336" lbTx="2.944016" tId="2" fbRx="2.947336" lbRx="2.949016" />
<p fId="2" fbTx="2.9566512" lbTx="2.9571152" tId="1" fbRx="2.9616512" lbRx="2.9621152" />
<p fId="0" fbTx="2.96" lbTx="2.960336" tId="1" fbRx="2.962" lbRx="2.962336" />
<p fId="1" fbTx="2.9621152" lbTx="2.962208" tId="2" fbRx="2.9821152" lbRx="2.982208" />
<p fId="1" fbTx="2.962336" lbTx="2.964016" tId="2" fbRx="2.967336" lbRx="2.969016" />
<p fId="0" fbTx="2.98" lbTx="2.980336" tId="1" fbRx="2.982" lbRx="2.982336" />
<p fId="2" fbTx="2.982208" lbTx="2.982672" tId="1" fbRx="2.987208" lbRx="2.987672" />
<p fId="1" fbTx="2.982336" lbTx="2.984016" tId="2" fbRx="2.987336" lbRx="2.989016" />
<p fId="1" fbTx="2.987672" lbTx="2.9877648" tId="2" fbRx="3.007672" lbRx="3.0077648" />
<p fId="0" fbTx="3" lbTx="3.000336" tId="1" fbRx="3.002" lbRx="3.002336" />
<p fId="1" fbTx="3.002336" lbTx="3.004016" tId="2" fbRx="3.007336" lbRx="3.009016" />
<p fId="2" fbTx="3.0077648" lbTx="3.0082288" tId="1" fbRx="3.0127648" lbRx="3.0132288" />
<p fId="1" fbTx="3.0132288" lbTx="3.0133216" tId="2" fbRx="3.0332288" lbRx="3.0333216" />
<p fId="0" fbTx="3.02" lbTx="3.020336" tId="1" fbRx="3.022" lbRx="3.022336" />
<p fId="1" fbTx="3.022336" lbTx="3.024016" tId="2" fbRx="3.027336" lbRx="3.029016" />
<p fId="2" fbTx="3.0333216" lbTx="3.0337856" tId="1" fbRx="3.0383216" lbRx="3.0387856" />
<p fId="1" fbTx="3.0387856" lbTx="3.0388784" tId="2" fbRx="3.0587856" lbRx="3.0588784" />
<p fId="0" fbTx="3.04" lbTx="3.040336" tId="1" fbRx="3.042" lbRx="3.042336" />
<p fId="1" fbTx="3.042336" lbTx="3.044016" tId="2" fbRx="3.047336" lbRx="3.049016" />
<p fId="2" fbTx="3.0588784" lbTx="3.0593424" tId="1" fbRx="3.0638784" lbRx="3.0643424" />
<p fId="0" fbTx="3.06" lbTx="3.060336" tId="1" fbRx="3.062" lbRx="3.062336" />
<p fId="1" fbTx="3.062336" lbTx="3.064016" tId="2" fbRx="3.067336" lbRx="3.069016" />
<p fId="1" fbTx="3.0643424" lbTx="3.0644352" tId="2" fbRx="3.0843424" lbRx="3.0844352" />
<p fId="0" fbTx="3.08" lbTx="3.080336" tId="1" fbRx="3.082" lbRx="3.082336" />
<p fId="1" fbTx="3.082336" lbTx="3.084016" tId="2" fbRx="3.087336" lbRx="3.089016" />
<p fId="2" fbTx="3.0844352" lbTx="3.0848992" tId="1" fbRx="3.0894352" lbRx="3.0898992" />
<p fId="1" fbTx="3.0898992" lbTx="3.089992" tId="2" fbRx="3.1098992" lbRx="3.109992" />
<p fId="0" fbTx="3.1" lbTx="3.100336" tId="1" fbRx="3.102" lbRx="3.102336" />
<p fId="1" fbTx="3.102336" lbTx="3.104016" tId="2" fbRx="3.107336" lbRx="3.109016" />
<p fId="2" fbTx="3.109992" lbTx="3.110456" tId="1" fbRx="3.114992" lbRx="3.115456" />
<p fId="1" fbTx="3.115456" lbTx="3.1155488" tId="2" fbRx="3.135456" lbRx="3.1355488" />
<p fId="0" fbTx="3.12" lbTx="3.120336" tId="1" fbRx="3.122" lbRx="3.122336" />
<p fId="1" fbTx="3.122336" lbTx="3.124016" tId="2" fbRx="3.127336" lbRx="3.129016" />
<p fId="2" fbTx="3.1355488" lbTx="3.1360128" tId="1" fbRx="3.1405488" lbRx="3.1410128" />
<p fId="0" fbTx="3.14" lbTx="3.140336" tId="1" fbRx="3.142" lbRx="3.142336" />
<p fId="1" fbTx="3.1410128" lbTx="3.1411056" tId="2" fbRx="3.1610128" lbRx="3.1611056" />
<p fId="1" fbTx="3.142336" lbTx="3.144016" tId="2" fbRx="3.147336" lbRx="3.149016" />
<p fId="0" fbTx="3.16" lbTx="3.160336" tId="1" fbRx="3.162" lbRx="3.162336" />
<p fId="2" fbTx="3.1611056" lbTx="3.1615696" tId="1" fbRx="3.1661056" lbRx="3.1665696" />
<p fId="1" fbTx="3.162336" lbTx="3.164016" tId="2" fbRx="3.167336" lbRx="3.169016" />
<p fId="1" fbTx="3.1665696" lbTx="3.1666624" tId="2" fbRx="3.1865696" lbRx="3.1866624" />
<p fId="0" fbTx="3.18" lbTx="3.180336" tId="1" fbRx="3.182" lbRx="3.182336" />
<p fId="1" fbTx="3.182336" lbTx="3.184016" tId="2" fbRx="3.187336" lbRx="3.189016" />
<p fId="2" fbTx="3.1866624" lbTx="3.1871264" tId="1" fbRx="3.1916624" lbRx="3.1921264" />
<p fId="1" fbTx="3.1921264" lbTx="3.1922192" tId="2" fbRx="3.2121264" lbRx="3.2122192" />
<p fId="0" fbTx="3.2" lbTx="3.200336" tId="1" fbRx="3.202" lbRx="3.202336" />
<p fId="1" fbTx="3.202336" lbTx="3.204016" tId="2" fbRx="3.207336" lbRx="3.209016" />
<p fId="2" fbTx="3.2122192" lbTx="3.2126832" tId="1" fbRx="3.2172192" lbRx="3.2176832" />
<p fId="1" fbTx="3.2176832" lbTx="3.217776" tId="2" fbRx="3.2376832" lbRx="3.237776" />
<p fId="0" fbTx="3.22" lbTx="3.220336" tId="1" fbRx="3.222" lbRx="3.222336" />
<p fId="1" fbTx="3.222336" lbTx="3.224016" tId="2" fbRx="3.227336" lbRx="3.229016" />
<p fId="2" fbTx="3.237776" lbTx="3.23824" tId="1" fbRx="3.242776" lbRx="3.24324" />
<p fId="0" fbTx="3.24" lbTx="3.240336" tId="1" fbRx="3.242" lbRx="3.242336" />
<p fId="1" fbTx="3.242336" lbTx="3.244016" tId="2" fbRx="3.247336" lbRx="3.249016" />
<p fId="1" fbTx="3.24324" lbTx="3.2433328" tId="2" fbRx="3.26324" lbRx="3.2633328" />
<p fId="0" fbTx="3.26" lbTx="3.260336" tId="1" fbRx="3.262" lbRx="3.262336" />
<p fId="1" fbTx="3.262336" lbTx="3.264016" tId="2" fbRx="3.267336" lbRx="3.269016" />
<p fId="2" fbTx="3.2633328" lbTx="3.2637968" tId="1" fbRx="3.2683328" lbRx="3.2687968" />
<p fId="1" fbTx="3.2687968" lbTx="3.2688896" tId="2" fbRx="3.2887968" lbRx="3.2888896" />
<p fId="0" fbTx="3.28" lbTx="3.280336" tId="1" fbRx="3.282" lbRx="3.282336" />
<p fId="1" fbTx="3.282336" lbTx="3.284016" tId="2" fbRx="3.287336" lbRx="3.289016" />
<p fId="2" fbTx="3.2888896" lbTx="3.2893536" tId="1" fbRx="3.2938896" lbRx="3.2943536" />
<p fId="1" fbTx="3.2943536" lbTx="3.2944464" tId="2" fbRx="3.3143536" lbRx="3.3144464" />
<p fId="0" fbTx="3.3" lbTx="3.300336" tId="1" fbRx="3.302" lbRx="3.302336" />
<p fId="1" fbTx="3.302336" lbTx="3.304016" tId="2" fbRx="3.307336" lbRx="3.309016" />
<p fId="2" fbTx="3.3144464" lbTx="3.3149104" tId="1" fbRx="3.3194464" lbRx="3.3199104" />
<p fId="1" fbTx="3.3199104" lbTx="3.3200032" tId="2" fbRx="3.3399104" lbRx="3.3400032" />
<p fId="0" fbTx="3.32" lbTx="3.320336" tId="1" fbRx="3.322" lbRx="3.322336" />
<p fId="1" fbTx="3.322336" lbTx="3.324016" tId="2" fbRx="3.327336" lbRx="3.329016" />
<p fId="0" fbTx="3.34" lbTx="3.340336" tId="1" fbRx="3.342" lbRx="3.342336" />
<p fId="1" fbTx="3.342336" lbTx="3.344016" tId="2" fbRx="3.347336" lbRx="3.349016" />
<p fId="0" fbTx="3.36" lbTx="3.360336" tId="1" fbRx="3.362" lbRx="3.362336" />
<p fId="1" fbTx="3.362336" lbTx="3.364016" tId="2" fbRx="3.367336" lbRx="3.369016" />
<p fId="0" fbTx="3.38" lbTx="3.380336" tId="1" fbRx="3.382" lbRx="3.382336" />
<p fId="1" fbTx="3.382336" lbTx="3.384016" tId="2" fbRx="3.387336" lbRx="3.389016" />
<p fId="0" fbTx="3.4" lbTx="3.400336" tId="1" fbRx="3.402" lbRx="3.402336" />
<p fId="1" fbTx="3.402336" lbTx="3.404016" tId="2" fbRx="3.407336" lbRx="3.409016" />
<p fId="0" fbTx="3.42" lbTx="3.420336" tId="1" fbRx="3.422" lbRx="3.422336" />
<p fId="1" fbTx="3.422336" lbTx="3.424016" tId="2" fbRx="3.427336" lbRx="3.429016" />
<p fId="0" fbTx="3.44" lbTx="3.440336" tId="1" fbRx="3.442" lbRx="3.442336" />
<p fId="1" fbTx="3.442336" lbTx="3.444016" tId="2" fbRx="3.447336" lbRx="3.449016" />
<p fId="0" fbTx="3.46" lbTx="3.460336" tId="1" fbRx="3.462" lbRx="3.462336" />
<p fId="1" fbTx="3.462336" lbTx="3.464016" tId="2" fbRx="3.467336" lbRx="3.469016" />
<p fId="0" fbTx="3.48" lbTx="3.480336" tId="1" fbRx="3.482" lbRx="3.482336" />
<p fId="1" fbTx="3.482336" lbTx="3.484016" tId="2" fbRx="3.487336" lbRx="3.489016" />
<p fId="0" fbTx="3.5" lbTx="3.500336" tId="1" fbRx="3.502" lbRx="3.502336" />
<p fId="1" fbTx="3.502336" lbTx="3.504016" tId="2" fbRx="3.507336" lbRx="3.509016" />
<p fId="0" fbTx="3.52" lbTx="3.520336" tId="1" fbRx="3.522" lbRx="3.522336" />
<p fId="1" fbTx="3.522336" lbTx="3.524016" tId="2" fbRx="3.527336" lbRx="3.529016" />
<p fId="0" fbTx="3.54" lbTx="3.540336" tId="1" fbRx="3.542" lbRx="3.542336" />
<p fId="1" fbTx="3.542336" lbTx="3.544016" tId="2" fbRx="3.547336" lbRx="3.549016" />
<p fId="0" fbTx="3.56" lbTx="3.560336" tId="1" fbRx="3.562" lbRx="3.562336" />
<p fId="1" fbTx="3.562336" lbTx="3.564016" tId="2" fbRx="3.567336" lbRx="3.569016" />
<p fId="0" fbTx="3.58" lbTx="3.580336" tId="1" fbRx="3.582" lbRx="3.582336" />
<p fId="1" fbTx="3.582336" lbTx="3.584016" tId="2" fbRx="3.587336" lbRx="3.589016" />
<p fId="0" fbTx="3.6" lbTx="3.600336" tId="1" fbRx="3.602" lbRx="3.602336" />
<p fId="1" fbTx="3.602336" lbTx="3.604016" tId="2" fbRx="3.607336" lbRx="3.609016" />
<p fId="0" fbTx="3.62" lbTx="3.620336" tId="1" fbRx="3.622" lbRx="3.622336" />
<p fId="1" fbTx="3.622336" lbTx="3.624016" tId="2" fbRx="3.627336" lbRx="3.629016" />
<p fId="0" fbTx="3.64" lbTx="3.640336" tId="1" fbRx="3.642" lbRx="3.642336" />
<p fId="1" fbTx="3.642336" lbTx="3.644016" tId="2" fbRx="3.647336" lbRx="3.649016" />
<p fId="0" fbTx="3.66" lbTx="3.660336" tId="1" fbRx="3.662" lbRx="3.662336" />
<p fId="1" fbTx="3.662336" lbTx="3.664016" tId="2" fbRx="3.667336" lbRx="3.669016" />
<p fId="0" fbTx="3.68" lbTx="3.680336" tId="1" fbRx="3.682" lbRx="3.682336" />
<p fId="1" fbTx="3.682336" lbTx="3.684016" tId="2" fbRx="3.687336" lbRx="3.689016" />
<p fId="0" fbTx="3.7" lbTx="3.700336" tId="1" fbRx="3.702" lbRx="3.702336" />
<p fId="1" fbTx="3.702336" lbTx="3.704016" tId="2" fbRx="3.707336" lbRx="3.709016" />
<p fId="0" fbTx="3.72" lbTx="3.720336" tId="1" fbRx="3.722" lbRx="3.722336" />
<p fId="1" fbTx="3.722336" lbTx="3.724016" tId="2" fbRx="3.727336" lbRx="3.729016" />
<p fId="0" fbTx="3.74" lbTx="3.740336" tId="1" fbRx="3.742" lbRx="3.742336" />
<p fId="1" fbTx="3.742336" lbTx="3.744016" tId="2" fbRx="3.747336" lbRx="3.749016" />
<p fId="0" fbTx="3.76" lbTx="3.760336" tId="1" fbRx="3.762" lbRx="3.762336" />
<p fId="1" fbTx="3.762336" lbTx="3.764016" tId="2" fbRx="3.767336" lbRx="3.769016" />
<p fId="0" fbTx="3.78" lbTx="3.780336" tId="1" fbRx="3.782" lbRx="3.782336" />
<p fId="1" fbTx="3.782336" lbTx="3.784016" tId="2" fbRx="3.787336" lbRx="3.789016" />
<p fId="0" fbTx="3.8" lbTx="3.800336" tId="1" fbRx="3.802" lbRx="3.802336" />
<p fId="1" fbTx="3.802336" lbTx="3.804016" tId="2" fbRx="3.807336" lbRx="3.809016" />
<p fId="0" fbTx="3.82" lbTx="3.820336" tId="1" fbRx="3.822" lbRx="3.822336" />
<p fId="1" fbTx="3.822336" lbTx="3.824016" tId="2" fbRx="3.827336" lbRx="3.829016" />
<p fId="0" fbTx="3.84" lbTx="3.840336" tId="1" fbRx="3.842" lbRx="3.842336" />
<p fId="1" fbTx="3.842336" lbTx="3.844016" tId="2" fbRx="3.847336" lbRx="3.849016" />
<p fId="0" fbTx="3.86" lbTx="3.860336" tId="1" fbRx="3.862" lbRx="3.862336" />
<p fId="1" fbTx="3.862336" lbTx="3.864016" tId="2" fbRx="3.867336" lbRx="3.869016" />
<p fId="0" fbTx="3.88" lbTx="3.880336" tId="1" fbRx="3.882" lbRx="3.882336" />
<p fId="1" fbTx="3.882336" lbTx="3.884016" tId="2" fbRx="3.887336" lbRx="3.889016" />
<p fId="0" fbTx="3.9" lbTx="3.900336" tId="1" fbRx="3.902" lbRx="3.902336" />
<p fId="1" fbTx="3.902336" lbTx="3.904016" tId="2" fbRx="3.907336" lbRx="3.909016" />
<p fId="0" fbTx="3.92" lbTx="3.920336" tId="1" fbRx="3.922" lbRx="3.922336" />
<p fId="1" fbTx="3.922336" lbTx="3.924016" tId="2" fbRx="3.927336" lbRx="3.929016" />
<p fId="0" fbTx="3.94" lbTx="3.940336" tId="1" fbRx="3.942" lbRx="3.942336" />
<p fId="1" fbTx="3.942336" lbTx="3.944016" tId="2" fbRx="3.947336" lbRx="3.949016" />
<p fId="0" fbTx="3.96" lbTx="3.960336" tId="1" fbRx="3.962" lbRx="3.962336" />
<p fId="1" fbTx="3.962336" lbTx="3.964016" tId="2" fbRx="3.967336" lbRx="3.969016" />
<p fId="0" fbTx="3.98" lbTx="3.980336" tId="1" fbRx="3.982" lbRx="3.982336" />
<p fId="1" fbTx="3.982336" lbTx="3.984016" tId="2" fbRx="3.987336" lbRx="3.989016" />
<p fId="0" fbTx="4" lbTx="4.000336" tId="1" fbRx="4.002" lbRx="4.002336" />
<p fId="1" fbTx="4.002336" lbTx="4.004016" tId="2" fbRx="4.007336" lbRx="4.009016" />
<p fId="0" fbTx="4.02" lbTx="4.020336" tId="1" fbRx="4.022" lbRx="4.022336" />
<p fId="1" fbTx="4.022336" lbTx="4.024016" tId="2" fbRx="4.027336" lbRx="4.029016" />
<p fId="0" fbTx="4.04" lbTx="4.040336" tId="1" fbRx="4.042" lbRx="4.042336" />
<p fId="1" fbTx="4.042336" lbTx="4.044016" tId="2" fbRx="4.047336" lbRx="4.049016" />
<p fId="0" fbTx="4.06" lbTx="4.060336" tId="1" fbRx="4.062" lbRx="4.062336" />
<p fId="1" fbTx="4.062336" lbTx="4.064016" tId="2" fbRx="4.067336" lbRx="4.069016" />
<p fId="0" fbTx="4.08" lbTx="4.080336" tId="1" fbRx="4.082" lbRx="4.082336" />
<p fId="1" fbTx="4.082336" lbTx="4.084016" tId="2" fbRx="4.087336" lbRx="4.089016" />
<p fId="0" fbTx="4.1" lbTx="4.100336" tId="1" fbRx="4.102" lbRx="4.102336" />
<p fId="1" fbTx="4.102336" lbTx="4.104016" tId="2" fbRx="4.107336" lbRx="4.109016" />
<p fId="0" fbTx="4.12" lbTx="4.120336" tId="1" fbRx="4.122" lbRx="4.122336" />
<p fId="1" fbTx="4.122336" lbTx="4.124016" tId="2" fbRx="4.127336" lbRx="4.129016" />
<p fId="0" fbTx="4.14" lbTx="4.140336" tId="1" fbRx="4.142" lbRx="4.142336" />
<p fId="1" fbTx="4.142336" lbTx="4.144016" tId="2" fbRx="4.147336" lbRx="4.149016" />
<p fId="0" fbTx="4.16" lbTx="4.160336" tId="1" fbRx="4.162" lbRx="4.162336" />
<p fId="1" fbTx="4.162336" lbTx="4.164016" tId="2" fbRx="4.167336" lbRx="4.169016" />
<p fId="0" fbTx="4.18" lbTx="4.180336" tId="1" fbRx="4.182" lbRx="4.182336" />
<p fId="1" fbTx="4.182336" lbTx="4.184016" tId="2" fbRx="4.187336" lbRx="4.189016" />
<p fId="0" fbTx="4.2" lbTx="4.200336" tId="1" fbRx="4.202" lbRx="4.202336" />
<p fId="1" fbTx="4.202336" lbTx="4.204016" tId="2" fbRx="4.207336" lbRx="4.209016" />
<p fId="0" fbTx="4.22" lbTx="4.220336" tId="1" fbRx="4.222" lbRx="4.222336" />
<p fId="1" fbTx="4.222336" lbTx="4.224016" tId="2" fbRx="4.227336" lbRx="4.229016" />
<p fId="0" fbTx="4.24" lbTx="4.240336" tId="1" fbRx="4.242" lbRx="4.242336" />
<p fId="1" fbTx="4.242336" lbTx="4.244016" tId="2" fbRx="4.247336" lbRx="4.249016" />
<p fId="0" fbTx="4.26" lbTx="4.260336" tId="1" fbRx="4.262" lbRx="4.262336" />
<p fId="1" fbTx="4.262336" lbTx="4.264016" tId="2" fbRx="4.267336" lbRx="4.269016" />
<p fId="0" fbTx="4.28" lbTx="4.280336" tId="1" fbRx="4.282" lbRx="4.282336" />
<p fId="1" fbTx="4.282336" lbTx="4.284016" tId="2" fbRx="4.287336" lbRx="4.289016" />
<p fId="0" fbTx="4.3" lbTx="4.300336" tId="1" fbRx="4.302" lbRx="4.302336" />
<p fId="1" fbTx="4.302336" lbTx="4.304016" tId="2" fbRx="4.307336" lbRx="4.309016" />
<p fId="0" fbTx="4.32" lbTx="4.320336" tId="1" fbRx="4.322" lbRx="4.322336" />
<p fId="1" fbTx="4.322336" lbTx="4.324016" tId="2" fbRx="4.327336" lbRx="4.329016" />
<p fId="0" fbTx="4.34" lbTx="4.340336" tId="1" fbRx="4.342" lbRx="4.342336" />
<p fId="1" fbTx="4.342336" lbTx="4.344016" tId="2" fbRx="4.347336" lbRx="4.349016" />
<p fId="0" fbTx="4.36" lbTx="4.360336" tId="1" fbRx="4.362" lbRx="4.362336" />
<p fId="1" fbTx="4.362336" lbTx="4.364016" tId="2" fbRx="4.367336" lbRx="4.369016" />
<p fId="0" fbTx="4.38" lbTx="4.380336" tId="1" fbRx="4.382" lbRx="4.382336" />
<p fId="1" fbTx="4.382336" lbTx="4.384016" tId="2" fbRx="4.387336" lbRx="4.389016" />
<p fId="0" fbTx="4.4" lbTx="4.400336" tId="1" fbRx="4.402" lbRx="4.402336" />
<p fId="1" fbTx="4.402336" lbTx="4.404016" tId="2" fbRx="4.407336" lbRx="4.409016" />
<p fId="0" fbTx="4.42" lbTx="4.420336" tId="1" fbRx="4.422" lbRx="4.422336" />
<p fId="1" fbTx="4.422336" lbTx="4.424016" tId="2" fbRx="4.427336" lbRx="4.429016" />
<p fId="0" fbTx="4.44" lbTx="4.440336" tId="1" fbRx="4.442" lbRx="4.442336" />
<p fId="1" fbTx="4.442336" lbTx="4.444016" tId="2" fbRx="4.447336" lbRx="4.449016" />
<p fId="0" fbTx="4.46" lbTx="4.460336" tId="1" fbRx="4.462" lbRx="4.462336" />
<p fId="1" fbTx="4.462336" lbTx="4.464016" tId="2" fbRx="4.467336" lbRx="4.469016" />
<p fId="0" fbTx="4.48" lbTx="4.480336" tId="1" fbRx="4.482" lbRx="4.482336" />
<p fId="1" fbTx="4.482336" lbTx="4.484016" tId="2" fbRx="4.487336" lbRx="4.489016" />
<p fId="0" fbTx="4.5" lbTx="4.500336" tId="1" fbRx="4.502" lbRx="4.502336" />
<p fId="1" fbTx="4.502336" lbTx="4.504016" tId="2" fbRx="4.507336" lbRx="4.509016" />
<p fId="0" fbTx="4.52" lbTx="4.520336" tId="1" fbRx="4.522" lbRx="4.522336" />
<p fId="1" fbTx="4.522336" lbTx="4.524016" tId="2" fbRx="4.527336" lbRx="4.529016" />
<p fId="0" fbTx="4.54" lbTx="4.540336" tId="1" fbRx="4.542" lbRx="4.542336" />
<p fId="1" fbTx="4.542336" lbTx="4.544016" tId="2" fbRx="4.547336" lbRx="4.549016" />
<p fId="0" fbTx="4.56" lbTx="4.560336" tId="1" fbRx="4.562" lbRx="4.562336" />
<p fId="1" fbTx="4.562336" lbTx="4.564016" tId="2" fbRx="4.567336" lbRx="4.569016" />
<p fId="0" fbTx="4.58" lbTx="4.580336" tId="1" fbRx="4.582" lbRx="4.582336" />
<p fId="1" fbTx="4.582336" lbTx="4.584016" tId="2" fbRx="4.587336" lbRx="4.589016" />
<p fId="0" fbTx="4.6" lbTx="4.600336" tId="1" fbRx="4.602" lbRx="4.602336" />
<p fId="1" fbTx="4.602336" lbTx="4.604016" tId="2" fbRx="4.607336" lbRx="4.609016" />
<p fId="0" fbTx="4.62" lbTx="4.620336" tId="1" fbRx="4.622" lbRx="4.622336" />
<p fId="1" fbTx="4.622336" lbTx="4.624016" tId="2" fbRx="4.627336" lbRx="4.629016" />
<p fId="0" fbTx="4.64" lbTx="4.640336" tId="1" fbRx="4.642" lbRx="4.642336" />
<p fId="1" fbTx="4.642336" lbTx="4.644016" tId="2" fbRx="4.647336" lbRx="4.649016" />
<p fId="0" fbTx="4.66" lbTx="4.660336" tId="1" fbRx="4.662" lbRx="4.662336" />
<p fId="1" fbTx="4.662336" lbTx="4.664016" tId="2" fbRx="4.667336" lbRx="4.669016" />
<p fId="0" fbTx="4.68" lbTx="4.680336" tId="1" fbRx="4.682" lbRx="4.682336" />
<p fId="1" fbTx="4.682336" lbTx="4.684016" tId="2" fbRx="4.687336" lbRx="4.689016" />
<p fId="0" fbTx="4.7" lbTx="4.700336" tId="1" fbRx="4.702" lbRx="4.702336" />
<p fId="1" fbTx="4.702336" lbTx="4.704016" tId="2" fbRx="4.707336" lbRx="4.709016" />
<p fId="0" fbTx="4.72" lbTx="4.720336" tId="1" fbRx="4.722" lbRx="4.722336" />
<p fId="1" fbTx="4.722336" lbTx="4.724016" tId="2" fbRx="4.727336" lbRx="4.729016" />
<p fId="0" fbTx="4.74" lbTx="4.740336" tId="1" fbRx="4.742" lbRx="4.742336" />
<p fId="1" fbTx="4.742336" lbTx="4.744016" tId="2" fbRx="4.747336" lbRx="4.749016" />
<p fId="0" fbTx="4.76" lbTx="4.760336" tId="1" fbRx="4.762" lbRx="4.762336" />
<p fId="1" fbTx="4.762336" lbTx="4.764016" tId="2" fbRx="4.767336" lbRx="4.769016" />
<p fId="0" fbTx="4.78" lbTx="4.780336" tId="1" fbRx="4.782" lbRx="4.782336" />
<p fId="1" fbTx="4.782336" lbTx="4.784016" tId="2" fbRx="4.787336" lbRx="4.789016" />
<p fId="0" fbTx="4.8" lbTx="4.800336" tId="1" fbRx="4.802" lbRx="4.802336" />
<p fId="1" fbTx="4.802336" lbTx="4.804016" tId="2" fbRx="4.807336" lbRx="4.809016" />
<p fId="0" fbTx="4.82" lbTx="4.820336" tId="1" fbRx="4.822" lbRx="4.822336" />
<p fId="1" fbTx="4.822336" lbTx="4.824016" tId="2" fbRx="4.827336" lbRx="4.829016" />
<p fId="0" fbTx="4.84" lbTx="4.840336" tId="1" fbRx="4.842" lbRx="4.842336" />
<p fId="1" fbTx="4.842336" lbTx="4.844016" tId="2" fbRx="4.847336" lbRx="4.849016" />
<p fId="0" fbTx="4.86" lbTx="4.860336" tId="1" fbRx="4.862" lbRx="4.862336" />
<p fId="1" fbTx="4.862336" lbTx="4.864016" tId="2" fbRx="4.867336" lbRx="4.869016" />
<p fId="0" fbTx="4.88" lbTx="4.880336" tId="1" fbRx="4.882" lbRx="4.882336" />
<p fId="1" fbTx="4.882336" lbTx="4.884016" tId="2" fbRx="4.887336" lbRx="4.889016" />
<p fId="0" fbTx="4.9" lbTx="4.900336" tId="1" fbRx="4.902" lbRx="4.902336" />
<p fId="1" fbTx="4.902336" lbTx="4.904016" tId="2" fbRx="4.907336" lbRx="4.909016" />
<p fId="0" fbTx="4.92" lbTx="4.920336" tId="1" fbRx="4.922" lbRx="4.922336" />
<p fId="1" fbTx="4.922336" lbTx="4.924016" tId="2" fbRx="4.927336" lbRx="4.929016" />
<p fId="0" fbTx="4.94" lbTx="4.940336" tId="1" fbRx="4.942" lbRx="4.942336" />
<p fId="1" fbTx="4.942336" lbTx="4.944016" tId="2" fbRx="4.947336" lbRx="4.949016" />
<p fId="0" fbTx="4.96" lbTx="4.960336" tId="1" fbRx="4.962" lbRx="4.962336" />
<p fId="1" fbTx="4.962336" lbTx="4.964016" tId="2" fbRx="4.967336" lbRx="4.969016" />
<p fId="0" fbTx="4.98" lbTx="4.980336" tId="1" fbRx="4.982" lbRx="4.982336" />
<p fId="1" fbTx="4.982336" lbTx="4.984016" tId="2" fbRx="4.987336" lbRx="4.989016" />
<p fId="0" fbTx="5" lbTx="5.000336" tId="1" fbRx="5.002" lbRx="5.002336" />
<p fId="1" fbTx="5.002336" lbTx="5.004016" tId="2" fbRx="5.007336" lbRx="5.009016" />
<p fId="0" fbTx="5.02" lbTx="5.020336" tId="1" fbRx="5.022" lbRx="5.022336" />
<p fId="1" fbTx="5.022336" lbTx="5.024016" tId="2" fbRx="5.027336" lbRx="5.029016" />
<p fId="0" fbTx="5.04" lbTx="5.040336" tId="1" fbRx="5.042" lbRx="5.042336" />
<p fId="1" fbTx="5.042336" lbTx="5.044016" tId="2" fbRx="5.047336" lbRx="5.049016" />
<p fId="0" fbTx="5.06" lbTx="5.060336" tId="1" fbRx="5.062" lbRx="5.062336" />
<p fId="1" fbTx="5.062336" lbTx="5.064016" tId="2" fbRx="5.067336" lbRx="5.069016" />
<p fId="0" fbTx="5.08" lbTx="5.080336" tId="1" fbRx="5.082" lbRx="5.082336" />
<p fId="1" fbTx="5.082336" lbTx="5.084016" tId="2" fbRx="5.087336" lbRx="5.089016" />
<p fId="0" fbTx="5.1" lbTx="5.100336" tId="1" fbRx="5.102" lbRx="5.102336" />
<p fId="1" fbTx="5.102336" lbTx="5.104016" tId="2" fbRx="5.107336" lbRx="5.109016" />
<p fId="0" fbTx="5.12" lbTx="5.120336" tId="1" fbRx="5.122" lbRx="5.122336" />
<p fId="1" fbTx="5.122336" lbTx="5.124016" tId="2" fbRx="5.127336" lbRx="5.129016" />
<p fId="0" fbTx="5.14" lbTx="5.140336" tId="1" fbRx="5.142" lbRx="5.142336" />
<p fId="1" fbTx="5.142336" lbTx="5.144016" tId="2" fbRx="5.147336" lbRx="5.149016" />
<p fId="0" fbTx="5.16" lbTx="5.160336" tId="1" fbRx="5.162" lbRx="5.162336" />
<p fId="1" fbTx="5.162336" lbTx="5.164016" tId="2" fbRx="5.167336" lbRx="5.169016" />
<p fId="0" fbTx="5.18" lbTx="5.180336" tId="1" fbRx="5.182" lbRx="5.182336" />
<p fId="1" fbTx="5.182336" lbTx="5.184016" tId="2" fbRx="5.187336" lbRx="5.189016" />
<p fId="0" fbTx="5.2" lbTx="5.200336" tId="1" fbRx="5.202" lbRx="5.202336" />
<p fId="1" fbTx="5.202336" lbTx="5.204016" tId="2" fbRx="5.207336" lbRx="5.209016" />
<p fId="0" fbTx="5.22" lbTx="5.220336" tId="1" fbRx="5.222" lbRx="5.222336" />
<p fId="1" fbTx="5.222336" lbTx="5.224016" tId="2" fbRx="5.227336" lbRx="5.229016" />
<p fId="0" fbTx="5.24" lbTx="5.240336" tId="1" fbRx="5.242" lbRx="5.242336" />
<p fId="1" fbTx="5.242336" lbTx="5.244016" tId="2" fbRx="5.247336" lbRx="5.249016" />
<p fId="0" fbTx="5.26" lbTx="5.260336" tId="1" fbRx="5.262" lbRx="5.262336" />
<p fId="1" fbTx="5.262336" lbTx="5.264016" tId="2" fbRx="5.267336" lbRx="5.269016" />
<p fId="0" fbTx="5.28" lbTx="5.280336" tId="1" fbRx="5.282" lbRx="5.282336" />
<p fId="1" fbTx="5.282336" lbTx="5.284016" tId="2" fbRx="5.287336" lbRx="5.289016" />
<p fId="0" fbTx="5.3" lbTx="5.300336" tId="1" fbRx="5.302" lbRx="5.302336" />
<p fId="1" fbTx="5.302336" lbTx="5.304016" tId="2" fbRx="5.307336" lbRx="5.309016" />
<p fId="0" fbTx="5.32" lbTx="5.320336" tId="1" fbRx="5.322" lbRx="5.322336" />
<p fId="1" fbTx="5.322336" lbTx="5.324016" tId="2" fbRx="5.327336" lbRx="5.329016" />
<p fId="0" fbTx="5.34" lbTx="5.340336" tId="1" fbRx="5.342" lbRx="5.342336" />
<p fId="1" fbTx="5.342336" lbTx="5.344016" tId="2" fbRx="5.347336" lbRx="5.349016" />
<p fId="0" fbTx="5.36" lbTx="5.360336" tId="1" fbRx="5.362" lbRx="5.362336" />
<p fId="1" fbTx="5.362336" lbTx="5.364016" tId="2" fbRx="5.367336" lbRx="5.369016" />
<p fId="0" fbTx="5.38" lbTx="5.380336" tId="1" fbRx="5.382" lbRx="5.382336" />
<p fId="1" fbTx="5.382336" lbTx="5.384016" tId="2" fbRx="5.387336" lbRx="5.389016" />
<p fId="0" fbTx="5.4" lbTx="5.400336" tId="1" fbRx="5.402" lbRx="5.402336" />
<p fId="1" fbTx="5.402336" lbTx="5.404016" tId="2" fbRx="5.407336" lbRx="5.409016" />
<p fId="0" fbTx="5.42" lbTx="5.420336" tId="1" fbRx="5.422" lbRx="5.422336" />
<p fId="1" fbTx="5.422336" lbTx="5.424016" tId="2" fbRx="5.427336" lbRx="5.429016" />
<p fId="0" fbTx="5.44" lbTx="5.440336" tId="1" fbRx="5.442" lbRx="5.442336" />
<p fId="1" fbTx="5.442336" lbTx="5.444016" tId="2" fbRx="5.447336" lbRx="5.449016" />
<p fId="0" fbTx="5.46" lbTx="5.460336" tId="1" fbRx="5.462" lbRx="5.462336" />
<p fId="1" fbTx="5.462336" lbTx="5.464016" tId="2" fbRx="5.467336" lbRx="5.469016" />
<p fId="0" fbTx="5.48" lbTx="5.480336" tId="1" fbRx="5.482" lbRx="5.482336" />
<p fId="1" fbTx="5.482336" lbTx="5.484016" tId="2" fbRx="5.487336" lbRx="5.489016" />
<p fId="0" fbTx="5.5" lbTx="5.5000928" tId="1" fbRx="5.502" lbRx="5.5020928" />
<p fId="0" fbTx="5.5000928" lbTx="5.5004288" tId="1" fbRx="5.5020928" lbRx="5.5024288" />
<p fId="1" fbTx="5.5020928" lbTx="5.5021856" tId="2" fbRx="5.5220928" lbRx="5.5221856" />
<p fId="1" fbTx="5.5024288" lbTx="5.5041088" tId="2" fbRx="5.5074288" lbRx="5.5091088" />
<p fId="0" fbTx="5.52" lbTx="5.520336" tId="1" fbRx="5.522" lbRx="5.522336" />
<p fId="2" fbTx="5.5221856" lbTx="5.5226496" tId="1" fbRx="5.5271856" lbRx="5.5276496" />
<p fId="1" fbTx="5.522336" lbTx="5.524016" tId="2" fbRx="5.527336" lbRx="5.529016" />
<p fId="2" fbTx="5.5226496" lbTx="5.5231136" tId="1" fbRx="5.5276496" lbRx="5.5281136" />
<p fId="1" fbTx="5.5276496" lbTx="5.5277424" tId="2" fbRx="5.5476496" lbRx="5.5477424" />
<p fId="1" fbTx="5.5281136" lbTx="5.5282064" tId="2" fbRx="5.5481136" lbRx="5.5482064" />
<p fId="0" fbTx="5.54" lbTx="5.540336" tId="1" fbRx="5.542" lbRx="5.542336" />
<p fId="1" fbTx="5.542336" lbTx="5.544016" tId="2" fbRx="5.547336" lbRx="5.549016" />
<p fId="2" fbTx="5.5477424" lbTx="5.5482064" tId="1" fbRx="5.5527424" lbRx="5.5532064" />
<p fId="2" fbTx="5.5482064" lbTx="5.5486704" tId="1" fbRx="5.5532064" lbRx="5.5536704" />
<p fId="1" fbTx="5.5532064" lbTx="5.5532992" tId="2" fbRx="5.5732064" lbRx="5.5732992" />
<p fId="1" fbTx="5.5536704" lbTx="5.5537632" tId="2" fbRx="5.5736704" lbRx="5.5737632" />
<p fId="0" fbTx="5.56" lbTx="5.560336" tId="1" fbRx="5.562" lbRx="5.562336" />
<p fId="1" fbTx="5.562336" lbTx="5.564016" tId="2" fbRx="5.567336" lbRx="5.569016" />
<p fId="2" fbTx="5.5732992" lbTx="5.5737632" tId="1" fbRx="5.5782992" lbRx="5.5787632" />
<p fId="2" fbTx="5.5737632" lbTx="5.5742272" tId="1" fbRx="5.5787632" lbRx="5.5792272" />
<p fId="1" fbTx="5.5787632" lbTx="5.578856" tId="2" fbRx="5.5987632" lbRx="5.598856" />
<p fId="1" fbTx="5.5792272" lbTx="5.57932" tId="2" fbRx="5.5992272" lbRx="5.59932" />
<p fId="0" fbTx="5.58" lbTx="5.580336" tId="1" fbRx="5.582" lbRx="5.582336" />
<p fId="1" fbTx="5.582336" lbTx="5.584016" tId="2" fbRx="5.587336" lbRx="5.589016" />
<p fId="2" fbTx="5.598856" lbTx="5.59932" tId="1" fbRx="5.603856" lbRx="5.60432" />
<p fId="2" fbTx="5.59932" lbTx="5.599784" tId="1" fbRx="5.60432" lbRx="5.604784" />
<p fId="0" fbTx="5.6" lbTx="5.600336" tId="1" fbRx="5.602" lbRx="5.602336" />
<p fId="1" fbTx="5.602336" lbTx="5.604016" tId="2" fbRx="5.607336" lbRx="5.609016" />
<p fId="1" fbTx="5.60432" lbTx="5.6044128" tId="2" fbRx="5.62432" lbRx="5.6244128" />
<p fId="1" fbTx="5.604784" lbTx="5.6048768" tId="2" fbRx="5.624784" lbRx="5.6248768" />
<p fId="0" fbTx="5.62" lbTx="5.620336" tId="1" fbRx="5.622" lbRx="5.622336" />
<p fId="1" fbTx="5.622336" lbTx="5.624016" tId="2" fbRx="5.627336" lbRx="5.629016" />
<p fId="2" fbTx="5.6244128" lbTx="5.6248768" tId="1" fbRx="5.6294128" lbRx="5.6298768" />
<p fId="2" fbTx="5.6248768" lbTx="5.6253408" tId="1" fbRx="5.6298768" lbRx="5.6303408" />
<p fId="1" fbTx="5.6298768" lbTx="5.6299696" tId="2" fbRx="5.6498768" lbRx="5.6499696" />
<p fId="1" fbTx="5.6303408" lbTx="5.6304336" tId="2" fbRx="5.6503408" lbRx="5.6504336" />
<p fId="0" fbTx="5.64" lbTx="5.640336" tId="1" fbRx="5.642" lbRx="5.642336" />
<p fId="1" fbTx="5.642336" lbTx="5.644016" tId="2" fbRx="5.647336" lbRx="5.649016" />
<p fId="2" fbTx="5.6499696" lbTx="5.6504336" tId="1" fbRx="5.6549696" lbRx="5.6554336" />
<p fId="2" fbTx="5.6504336" lbTx="5.6508976" tId="1" fbRx="5.6554336" lbRx="5.6558976" />
<p fId="1" fbTx="5.6554336" lbTx="5.6555264" tId="2" fbRx="5.6754336" lbRx="5.6755264" />
<p fId="1" fbTx="5.6558976" lbTx="5.6559904" tId="2" fbRx="5.6758976" lbRx="5.6759904" />
<p fId="0" fbTx="5.66" lbTx="5.660336" tId="1" fbRx="5.662" lbRx="5.662336" />
<p fId="1" fbTx="5.662336" lbTx="5.664016" tId="2" fbRx="5.667336" lbRx="5.669016" />
<p fId="2" fbTx="5.6755264" lbTx="5.6759904" tId="1" fbRx="5.6805264" lbRx="5.6809904" />
<p fId="2" fbTx="5.6759904" lbTx="5.6764544" tId="1" fbRx="5.6809904" lbRx="5.6814544" />
<p fId="0" fbTx="5.68" lbTx="5.680336" tId="1" fbRx="5.682" lbRx="5.682336" />
<p fId="1" fbTx="5.6809904" lbTx="5.6810832" tId="2" fbRx="5.7009904" lbRx="5.7010832" />
<p fId="1" fbTx="5.6814544" lbTx="5.6815472" tId="2" fbRx="5.7014544" lbRx="5.7015472" />
<p fId="1" fbTx="5.682336" lbTx="5.684016" tId="2" fbRx="5.687336" lbRx="5.689016" />
<p fId="0" fbTx="5.7" lbTx="5.700336" tId="1" fbRx="5.702" lbRx="5.702336" />
<p fId="2" fbTx="5.7010832" lbTx="5.7015472" tId="1" fbRx="5.7060832" lbRx="5.7065472" />
<p fId="2" fbTx="5.7015472" lbTx="5.7020112" tId="1" fbRx="5.7065472" lbRx="5.7070112" />
<p fId="1" fbTx="5.702336" lbTx="5.704016" tId="2" fbRx="5.707336" lbRx="5.709016" />
<p fId="1" fbTx="5.7065472" lbTx="5.70664" tId="2" fbRx="5.7265472" lbRx="5.72664" />
<p fId="1" fbTx="5.7070112" lbTx="5.707104" tId="2" fbRx="5.7270112" lbRx="5.727104" />
<p fId="0" fbTx="5.72" lbTx="5.720336" tId="1" fbRx="5.722" lbRx="5.722336" />
<p fId="1" fbTx="5.722336" lbTx="5.724016" tId="2" fbRx="5.727336" lbRx="5.729016" />
<p fId="2" fbTx="5.72664" lbTx="5.727104" tId="1" fbRx="5.73164" lbRx="5.732104" />
<p fId="2" fbTx="5.727104" lbTx="5.727568" tId="1" fbRx="5.732104" lbRx="5.732568" />
<p fId="1" fbTx="5.732104" lbTx="5.7321968" tId="2" fbRx="5.752104" lbRx="5.7521968" />
<p fId="1" fbTx="5.732568" lbTx="5.7326608" tId="2" fbRx="5.752568" lbRx="5.7526608" />
<p fId="0" fbTx="5.74" lbTx="5.740336" tId="1" fbRx="5.742" lbRx="5.742336" />
<p fId="1" fbTx="5.742336" lbTx="5.744016" tId="2" fbRx="5.747336" lbRx="5.749016" />
<p fId="2" fbTx="5.7521968" lbTx="5.7526608" tId="1" fbRx="5.7571968" lbRx="5.7576608" />
<p fId="2" fbTx="5.7526608" lbTx="5.7531248" tId="1" fbRx="5.7576608" lbRx="5.7581248" />
<p fId="1" fbTx="5.7576608" lbTx="5.7577536" tId="2" fbRx="5.7776608" lbRx="5.7777536" />
<p fId="1" fbTx="5.7581248" lbTx="5.7582176" tId="2" fbRx="5.7781248" lbRx="5.7782176" />
<p fId="0" fbTx="5.76" lbTx="5.760336" tId="1" fbRx="5.762" lbRx="5.762336" />
<p fId="1" fbTx="5.762336" lbTx="5.764016" tId="2" fbRx="5.767336" lbRx="5.769016" />
<p fId="2" fbTx="5.7777536" lbTx="5.7782176" tId="1" fbRx="5.7827536" lbRx="5.7832176" />
<p fId="2" fbTx="5.7782176" lbTx="5.7786816" tId="1" fbRx="5.7832176" lbRx="5.7836816" />
<p fId="0" fbTx="5.78" lbTx="5.780336" tId="1" fbRx="5.782" lbRx="5.782336" />
<p fId="1" fbTx="5.782336" lbTx="5.784016" tId="2" fbRx="5.787336" lbRx="5.789016" />
<p fId="1" fbTx="5.7832176" lbTx="5.7833104" tId="2" fbRx="5.8032176" lbRx="5.8033104" />
<p fId="1" fbTx="5.7836816" lbTx="5.7837744" tId="2" fbRx="5.8036816" lbRx="5.8037744" />
<p fId="0" fbTx="5.8" lbTx="5.800336" tId="1" fbRx="5.802" lbRx="5.802336" />
<p fId="1" fbTx="5.802336" lbTx="5.804016" tId="2" fbRx="5.807336" lbRx="5.809016" />
<p fId="2" fbTx="5.8033104" lbTx="5.8037744" tId="1" fbRx="5.8083104" lbRx="5.8087744" />
<p fId="2" fbTx="5.8037744" lbTx="5.8042384" tId="1" fbRx="5.8087744" lbRx="5.8092384" />
<p fId="1" fbTx="5.8087744" lbTx="5.8088672" tId="2" fbRx="5.8287744" lbRx="5.8288672" />
<p fId="1" fbTx="5.8092384" lbTx="5.8093312" tId="2" fbRx="5.8292384" lbRx="5.8293312" />
<p fId="0" fbTx="5.82" lbTx="5.820336" tId="1" fbRx="5.822" lbRx="5.822336" />
<p fId="1" fbTx="5.822336" lbTx="5.824016" tId="2" fbRx="5.827336" lbRx="5.829016" />
<p fId="2" fbTx="5.8288672" lbTx="5.8293312" tId="1" fbRx="5.8338672" lbRx="5.8343312" />
<p fId="2" fbTx="5.8293312" lbTx="5.8297952" tId="1" fbRx="5.8343312" lbRx="5.8347952" />
<p fId="1" fbTx="5.8343312" lbTx="5.834424" tId="2" fbRx="5.8543312" lbRx="5.854424" />
<p fId="1" fbTx="5.8347952" lbTx="5.834888" tId="2" fbRx="5.8547952" lbRx="5.854888" />
<p fId="0" fbTx="5.84" lbTx="5.840336" tId="1" fbRx="5.842" lbRx="5.842336" />
<p fId="1" fbTx="5.842336" lbTx="5.844016" tId="2" fbRx="5.847336" lbRx="5.849016" />
<p fId="2" fbTx="5.854424" lbTx="5.854888" tId="1" fbRx="5.859424" lbRx="5.859888" />
<p fId="2" fbTx="5.854888" lbTx="5.855352" tId="1" fbRx="5.859888" lbRx="5.860352" />
<p fId="1" fbTx="5.859888" lbTx="5.8599808" tId="2" fbRx="5.879888" lbRx="5.8799808" />
<p fId="0" fbTx="5.86" lbTx="5.860336" tId="1" fbRx="5.862" lbRx="5.862336" />
<p fId="1" fbTx="5.860352" lbTx="5.8604448" tId="2" fbRx="5.880352" lbRx="5.8804448" />
<p fId="1" fbTx="5.862336" lbTx="5.864016" tId="2" fbRx="5.867336" lbRx="5.869016" />
<p fId="2" fbTx="5.8799808" lbTx="5.8804448" tId="1" fbRx="5.8849808" lbRx="5.8854448" />
<p fId="0" fbTx="5.88" lbTx="5.880336" tId="1" fbRx="5.882" lbRx="5.882336" />
<p fId="2" fbTx="5.8804448" lbTx="5.8809088" tId="1" fbRx="5.8854448" lbRx="5.8859088" />
<p fId="1" fbTx="5.882336" lbTx="5.884016" tId="2" fbRx="5.887336" lbRx="5.889016" />
<p fId="1" fbTx="5.8854448" lbTx="5.8855376" tId="2" fbRx="5.9054448" lbRx="5.9055376" />
<p fId="1" fbTx="5.8859088" lbTx="5.8860016" tId="2" fbRx="5.9059088" lbRx="5.9060016" />
<p fId="0" fbTx="5.9" lbTx="5.900336" tId="1" fbRx="5.902" lbRx="5.902336" />
<p fId="1" fbTx="5.902336" lbTx="5.904016" tId="2" fbRx="5.907336" lbRx="5.909016" />
<p fId="2" fbTx="5.9055376" lbTx="5.9060016" tId="1" fbRx="5.9105376" lbRx="5.9110016" />
<p fId="2" fbTx="5.9060016" lbTx="5.9064656" tId="1" fbRx="5.9110016" lbRx="5.9114656" />
<p fId="1" fbTx="5.9110016" lbTx="5.9110944" tId="2" fbRx="5.9310016" lbRx="5.9310944" />
<p fId="1" fbTx="5.9114656" lbTx="5.9115584" tId="2" fbRx="5.9314656" lbRx="5.9315584" />
<p fId="0" fbTx="5.92" lbTx="5.920336" tId="1" fbRx="5.922" lbRx="5.922336" />
<p fId="1" fbTx="5.922336" lbTx="5.924016" tId="2" fbRx="5.927336" lbRx="5.929016" />
<p fId="2" fbTx="5.9310944" lbTx="5.9315584" tId="1" fbRx="5.9360944" lbRx="5.9365584" />
<p fId="2" fbTx="5.9315584" lbTx="5.9320224" tId="1" fbRx="5.9365584" lbRx="5.9370224" />
<p fId="1" fbTx="5.9365584" lbTx="5.9366512" tId="2" fbRx="5.9565584" lbRx="5.9566512" />
<p fId="1" fbTx="5.9370224" lbTx="5.9371152" tId="2" fbRx="5.9570224" lbRx="5.9571152" />
<p fId="0" fbTx="5.94" lbTx="5.940336" tId="1" fbRx="5.942" lbRx="5.942336" />
<p fId="1" fbTx="5.942336" lbTx="5.944016" tId="2" fbRx="5.947336" lbRx="5.949016" />
<p fId="2" fbTx="5.9566512" lbTx="5.9571152" tId="1" fbRx="5.9616512" lbRx="5.9621152" />
<p fId="2" fbTx="5.9571152" lbTx="5.9575792" tId="1" fbRx="5.9621152" lbRx="5.9625792" />
<p fId="0" fbTx="5.96" lbTx="5.960336" tId="1" fbRx="5.962" lbRx="5.962336" />
<p fId="1" fbTx="5.9621152" lbTx="5.962208" tId="2" fbRx="5.9821152" lbRx="5.982208" />
<p fId="1" fbTx="5.962336" lbTx="5.964016" tId="2" fbRx="5.967336" lbRx="5.969016" />
<p fId="1" fbTx="5.9625792" lbTx="5.962672" tId="2" fbRx="5.9825792" lbRx="5.982672" />
<p fId="0" fbTx="5.98" lbTx="5.980336" tId="1" fbRx="5.982" lbRx="5.982336" />
<p fId="2" fbTx="5.982208" lbTx="5.982672" tId="1" fbRx="5.987208" lbRx="5.987672" />
<p fId="1" fbTx="5.982336" lbTx="5.984016" tId="2" fbRx="5.987336" lbRx="5.989016" />
<p fId="2" fbTx="5.982672" lbTx="5.983136" tId="1" fbRx="5.987672" lbRx="5.988136" />
<p fId="1" fbTx="5.987672" lbTx="5.9877648" tId="2" fbRx="6.007672" lbRx="6.0077648" />
<p fId="1" fbTx="5.988136" lbTx="5.9882288" tId="2" fbRx="6.008136" lbRx="6.0082288" />
<p fId="0" fbTx="6" lbTx="6.000336" tId="1" fbRx="6.002" lbRx="6.002336" />
<p fId="1" fbTx="6.002336" lbTx="6.004016" tId="2" fbRx="6.007336" lbRx="6.009016" />
<p fId="2" fbTx="6.0077648" lbTx="6.0082288" tId="1" fbRx="6.0127648" lbRx="6.0132288" />
<p fId="2" fbTx="6.0082288" lbTx="6.0086928" tId="1" fbRx="6.0132288" lbRx="6.0136928" />
<p fId="1" fbTx="6.0132288" lbTx="6.0133216" tId="2" fbRx="6.0332288" lbRx="6.0333216" />
<p fId="1" fbTx="6.0136928" lbTx="6.0137856" tId="2" fbRx="6.0336928" lbRx="6.0337856" />
<p fId="0" fbTx="6.02" lbTx="6.020336" tId="1" fbRx="6.022" lbRx="6.022336" />
<p fId="1" fbTx="6.022336" lbTx="6.024016" tId="2" fbRx="6.027336" lbRx="6.029016" />
<p fId="2" fbTx="6.0333216" lbTx="6.0337856" tId="1" fbRx="6.0383216" lbRx="6.0387856" />
<p fId="2" fbTx="6.0337856" lbTx="6.0342496" tId="1" fbRx="6.0387856" lbRx="6.0392496" />
<p fId="1" fbTx="6.0387856" lbTx="6.0388784" tId="2" fbRx="6.0587856" lbRx="6.0588784" />
<p fId="1" fbTx="6.0392496" lbTx="6.0393424" tId="2" fbRx="6.0592496" lbRx="6.0593424" />
<p fId="0" fbTx="6.04" lbTx="6.040336" tId="1" fbRx="6.042" lbRx="6.042336" />
<p fId="1" fbTx="6.042336" lbTx="6.044016" tId="2" fbRx="6.047336" lbRx="6.049016" />
<p fId="2" fbTx="6.0588784" lbTx="6.0593424" tId="1" fbRx="6.0638784" lbRx="6.0643424" />
<p fId="2" fbTx="6.0593424" lbTx="6.0598064" tId="1" fbRx="6.0643424" lbRx="6.0648064" />
<p fId="0" fbTx="6.06" lbTx="6.060336" tId="1" fbRx="6.062" lbRx="6.062336" />
<p fId="1" fbTx="6.062336" lbTx="6.064016" tId="2" fbRx="6.067336" lbRx="6.069016" />
<p fId="1" fbTx="6.0643424" lbTx="6.0644352" tId="2" fbRx="6.0843424" lbRx="6.0844352" />
<p fId="1" fbTx="6.0648064" lbTx="6.0648992" tId="2" fbRx="6.0848064" lbRx="6.0848992" />
<p fId="0" fbTx="6.08" lbTx="6.080336" tId="1" fbRx="6.082" lbRx="6.082336" />
<p fId="1" fbTx="6.082336" lbTx="6.084016" tId="2" fbRx="6.087336" lbRx="6.089016" />
<p fId="2" fbTx="6.0844352" lbTx="6.0848992" tId="1" fbRx="6.0894352" lbRx="6.0898992" />
<p fId="2" fbTx="6.0848992" lbTx="6.0853632" tId="1" fbRx="6.0898992" lbRx="6.0903632" />
<p fId="1" fbTx="6.0898992" lbTx="6.089992" tId="2" fbRx="6.1098992" lbRx="6.109992" />
<p fId="1" fbTx="6.0903632" lbTx="6.090456" tId="2" fbRx="6.1103632" lbRx="6.110456" />
<p fId="0" fbTx="6.1" lbTx="6.100336" tId="1" fbRx="6.102" lbRx="6.102336" />
<p fId="1" fbTx="6.102336" lbTx="6.104016" tId="2" fbRx="6.107336" lbRx="6.109016" />
<p fId="2" fbTx="6.109992" lbTx="6.110456" tId="1" fbRx="6.114992" lbRx="6.115456" />
<p fId="2" fbTx="6.110456" lbTx="6.11092" tId="1" fbRx="6.115456" lbRx="6.11592" />
<p fId="1" fbTx="6.115456" lbTx="6.1155488" tId="2" fbRx="6.135456" lbRx="6.1355488" />
<p fId="1" fbTx="6.11592" lbTx="6.1160128" tId="2" fbRx="6.13592" lbRx="6.1360128" />
<p fId="0" fbTx="6.12" lbTx="6.120336" tId="1" fbRx="6.122" lbRx="6.122336" />
<p fId="1" fbTx="6.122336" lbTx="6.124016" tId="2" fbRx="6.127336" lbRx="6.129016" />
<p fId="2" fbTx="6.1355488" lbTx="6.1360128" tId="1" fbRx="6.1405488" lbRx="6.1410128" />
<p fId="2" fbTx="6.1360128" lbTx="6.1364768" tId="1" fbRx="6.1410128" lbRx="6.1414768" />
<p fId="0" fbTx="6.14" lbTx="6.140336" tId="1" fbRx="6.142" lbRx="6.142336" />
<p fId="1" fbTx="6.1410128" lbTx="6.1411056" tId="2" fbRx="6.1610128" lbRx="6.1611056" />
<p fId="1" fbTx="6.1414768" lbTx="6.1415696" tId="2" fbRx="6.1614768" lbRx="6.1615696" />
<p fId="1" fbTx="6.142336" lbTx="6.144016" tId="2" fbRx="6.147336" lbRx="6.149016" />
<p fId="0" fbTx="6.16" lbTx="6.160336" tId="1" fbRx="6.162" lbRx="6.162336" />
<p fId="2" fbTx="6.1611056" lbTx="6.1615696" tId="1" fbRx="6.1661056" lbRx="6.1665696" />
<p fId="2" fbTx="6.1615696" lbTx="6.1620336" tId="1" fbRx="6.1665696" lbRx="6.1670336" />
<p fId="1" fbTx="6.162336" lbTx="6.164016" tId="2" fbRx="6.167336" lbRx="6.169016" />
<p fId="1" fbTx="6.1665696" lbTx="6.1666624" tId="2" fbRx="6.1865696" lbRx="6.1866624" />
<p fId="1" fbTx="6.1670336" lbTx="6.1671264" tId="2" fbRx="6.1870336" lbRx="6.1871264" />
<p fId="0" fbTx="6.18" lbTx="6.180336" tId="1" fbRx="6.182" lbRx="6.182336" />
<p fId="1" fbTx="6.182336" lbTx="6.184016" tId="2" fbRx="6.187336" lbRx="6.189016" />
<p fId="2" fbTx="6.1866624" lbTx="6.1871264" tId="1" fbRx="6.1916624" lbRx="6.1921264" />
<p fId="2" fbTx="6.1871264" lbTx="6.1875904" tId="1" fbRx="6.1921264" lbRx="6.1925904" />
<p fId="1" fbTx="6.1921264" lbTx="6.1922192" tId="2" fbRx="6.2121264" lbRx="6.2122192" />
<p fId="1" fbTx="6.1925904" lbTx="6.1926832" tId="2" fbRx="6.2125904" lbRx="6.2126832" />
<p fId="0" fbTx="6.2" lbTx="6.200336" tId="1" fbRx="6.202" lbRx="6.202336" />
<p fId="1" fbTx="6.202336" lbTx="6.204016" tId="2" fbRx="6.207336" lbRx="6.209016" />
<p fId="2" fbTx="6.2122192" lbTx="6.2126832" tId="1" fbRx="6.2172192" lbRx="6.2176832" />
<p fId="2" fbTx="6.2126832" lbTx="6.2131472" tId="1" fbRx="6.2176832" lbRx="6.2181472" />
<p fId="1" fbTx="6.2176832" lbTx="6.217776" tId="2" fbRx="6.2376832" lbRx="6.237776" />
<p fId="1" fbTx="6.2181472" lbTx="6.21824" tId="2" fbRx="6.2381472" lbRx="6.23824" />
<p fId="0" fbTx="6.22" lbTx="6.220336" tId="1" fbRx="6.222" lbRx="6.222336" />
<p fId="1" fbTx="6.222336" lbTx="6.224016" tId="2" fbRx="6.227336" lbRx="6.229016" />
<p fId="2" fbTx="6.237776" lbTx="6.23824" tId="1" fbRx="6.242776" lbRx="6.24324" />
<p fId="2" fbTx="6.23824" lbTx="6.238704" tId="1" fbRx="6.24324" lbRx="6.243704" />
<p fId="0" fbTx="6.24" lbTx="6.240336" tId="1" fbRx="6.242" lbRx="6.242336" />
<p fId="1" fbTx="6.242336" lbTx="6.244016" tId="2" fbRx="6.247336" lbRx="6.249016" />
<p fId="1" fbTx="6.24324" lbTx="6.2433328" tId="2" fbRx="6.26324" lbRx="6.2633328" />
<p fId="1" fbTx="6.243704" lbTx="6.2437968" tId="2" fbRx="6.263704" lbRx="6.2637968" />
<p fId="0" fbTx="6.26" lbTx="6.260336" tId="1" fbRx="6.262" lbRx="6.262336" />
<p fId="1" fbTx="6.262336" lbTx="6.264016" tId="2" fbRx="6.267336" lbRx="6.269016" />
<p fId="2" fbTx="6.2633328" lbTx="6.2637968" tId="1" fbRx="6.2683328" lbRx="6.2687968" />
<p fId="2" fbTx="6.2637968" lbTx="6.2642608" tId="1" fbRx="6.2687968" lbRx="6.2692608" />
<p fId="1" fbTx="6.2687968" lbTx="6.2688896" tId="2" fbRx="6.2887968" lbRx="6.2888896" />
<p fId="1" fbTx="6.2692608" lbTx="6.2693536" tId="2" fbRx="6.2892608" lbRx="6.2893536" />
<p fId="0" fbTx="6.28" lbTx="6.280336" tId="1" fbRx="6.282" lbRx="6.282336" />
<p fId="1" fbTx="6.282336" lbTx="6.284016" tId="2" fbRx="6.287336" lbRx="6.289016" />
<p fId="2" fbTx="6.2888896" lbTx="6.2893536" tId="1" fbRx="6.2938896" lbRx="6.2943536" />
<p fId="2" fbTx="6.2893536" lbTx="6.2898176" tId="1" fbRx="6.2943536" lbRx="6.2948176" />
<p fId="1" fbTx="6.2943536" lbTx="6.2944464" tId="2" fbRx="6.3143536" lbRx="6.3144464" />
<p fId="1" fbTx="6.2948176" lbTx="6.2949104" tId="2" fbRx="6.3148176" lbRx="6.3149104" />
<p fId="0" fbTx="6.3" lbTx="6.300336" tId="1" fbRx="6.302" lbRx="6.302336" />
<p fId="1" fbTx="6.302336" lbTx="6.304016" tId="2" fbRx="6.307336" lbRx="6.309016" />
<p fId="2" fbTx="6.3144464" lbTx="6.3149104" tId="1" fbRx="6.3194464" lbRx="6.3199104" />
<p fId="2" fbTx="6.3149104" lbTx="6.3153744" tId="1" fbRx="6.3199104" lbRx="6.3203744" />
<p fId="1" fbTx="6.3199104" lbTx="6.3200032" tId="2" fbRx="6.3399104" lbRx="6.3400032" />
<p fId="0" fbTx="6.32" lbTx="6.320336" tId="1" fbRx="6.322" lbRx="6.322336" />
<p fId="1" fbTx="6.3203744" lbTx="6.3204672" tId="2" fbRx="6.3403744" lbRx="6.3404672" />
<p fId="1" fbTx="6.322336" lbTx="6.324016" tId="2" fbRx="6.327336" lbRx="6.329016" />
<p fId="0" fbTx="6.34" lbTx="6.340336" tId="1" fbRx="6.342" lbRx="6.342336" />
<p fId="1" fbTx="6.342336" lbTx="6.344016" tId="2" fbRx="6.347336" lbRx="6.349016" />
<p fId="0" fbTx="6.36" lbTx="6.360336" tId="1" fbRx="6.362" lbRx="6.362336" />
<p fId="1" fbTx="6.362336" lbTx="6.364016" tId="2" fbRx="6.367336" lbRx="6.369016" />
<p fId="0" fbTx="6.38" lbTx="6.380336" tId="1" fbRx="6.382" lbRx="6.382336" />
<p fId="1" fbTx="6.382336" lbTx="6.384016" tId="2" fbRx="6.387336" lbRx="6.389016" />
<p fId="0" fbTx="6.4" lbTx="6.400336" tId="1" fbRx="6.402" lbRx="6.402336" />
<p fId="1" fbTx="6.402336" lbTx="6.404016" tId="2" fbRx="6.407336" lbRx="6.409016" />
<p fId="0" fbTx="6.42" lbTx="6.420336" tId="1" fbRx="6.422" lbRx="6.422336" />
<p fId="1" fbTx="6.422336" lbTx="6.424016" tId="2" fbRx="6.427336" lbRx="6.429016" />
<p fId="0" fbTx="6.44" lbTx="6.440336" tId="1" fbRx="6.442" lbRx="6.442336" />
<p fId="1" fbTx="6.442336" lbTx="6.444016" tId="2" fbRx="6.447336" lbRx="6.449016" />
<p fId="0" fbTx="6.46" lbTx="6.460336" tId="1" fbRx="6.462" lbRx="6.462336" />
<p fId="1" fbTx="6.462336" lbTx="6.464016" tId="2" fbRx="6.467336" lbRx="6.469016" />
<p fId="0" fbTx="6.48" lbTx="6.480336" tId="1" fbRx="6.482" lbRx="6.482336" />
<p fId="1" fbTx="6.482336" lbTx="6.484016" tId="2" fbRx="6.487336" lbRx="6.489016" />
<p fId="0" fbTx="6.5" lbTx="6.500336" tId="1" fbRx="6.502" lbRx="6.502336" />
<p fId="1" fbTx="6.502336" lbTx="6.504016" tId="2" fbRx="6.507336" lbRx="6.509016" />
<p fId="0" fbTx="6.52" lbTx="6.520336" tId="1" fbRx="6.522" lbRx="6.522336" />
<p fId="1" fbTx="6.522336" lbTx="6.524016" tId="2" fbRx="6.527336" lbRx="6.529016" />
<p fId="0" fbTx="6.54" lbTx="6.540336" tId="1" fbRx="6.542" lbRx="6.542336" />
<p fId="1" fbTx="6.542336" lbTx="6.544016" tId="2" fbRx="6.547336" lbRx="6.549016" />
<p fId="0" fbTx="6.56" lbTx="6.560336" tId="1" fbRx="6.562" lbRx="6.562336" />
<p fId="1" fbTx="6.562336" lbTx="6.564016" tId="2" fbRx="6.567336" lbRx="6.569016" />
<p fId="0" fbTx="6.58" lbTx="6.580336" tId="1" fbRx="6.582" lbRx="6.582336" />
<p fId="1" fbTx="6.582336" lbTx="6.584016" tId="2" fbRx="6.587336" lbRx="6.589016" />
<p fId="0" fbTx="6.6" lbTx="6.600336" tId="1" fbRx="6.602" lbRx="6.602336" />
<p fId="1" fbTx="6.602336" lbTx="6.604016" tId="2" fbRx="6.607336" lbRx="6.609016" />
<p fId="0" fbTx="6.62" lbTx="6.620336" tId="1" fbRx="6.622" lbRx="6.622336" />
<p fId="1" fbTx="6.622336" lbTx="6.624016" tId="2" fbRx="6.627336" lbRx="6.629016" />
<p fId="0" fbTx="6.64" lbTx="6.640336" tId="1" fbRx="6.642" lbRx="6.642336" />
<p fId="1" fbTx="6.642336" lbTx="6.644016" tId="2" fbRx="6.647336" lbRx="6.649016" />
<p fId="0" fbTx="6.66" lbTx="6.660336" tId="1" fbRx="6.662" lbRx="6.662336" />
<p fId="1" fbTx="6.662336" lbTx="6.664016" tId="2" fbRx="6.667336" lbRx="6.669016" />
<p fId="0" fbTx="6.68" lbTx="6.680336" tId="1" fbRx="6.682" lbRx="6.682336" />
<p fId="1" fbTx="6.682336" lbTx="6.684016" tId="2" fbRx="6.687336" lbRx="6.689016" />
<p fId="0" fbTx="6.7" lbTx="6.700336" tId="1" fbRx="6.702" lbRx="6.702336" />
<p fId="1" fbTx="6.702336" lbTx="6.704016" tId="2" fbRx="6.707336" lbRx="6.709016" />
<p fId="0" fbTx="6.72" lbTx="6.720336" tId="1" fbRx="6.722" lbRx="6.722336" />
<p fId="1" fbTx="6.722336" lbTx="6.724016" tId="2" fbRx="6.727336" lbRx="6.729016" />
<p fId="0" fbTx="6.74" lbTx="6.740336" tId="1" fbRx="6.742" lbRx="6.742336" />
<p fId="1" fbTx="6.742336" lbTx="6.744016" tId="2" fbRx="6.747336" lbRx="6.749016" />
<p fId="0" fbTx="6.76" lbTx="6.760336" tId="1" fbRx="6.762" lbRx="6.762336" />
<p fId="1" fbTx="6.762336" lbTx="6.764016" tId="2" fbRx="6.767336" lbRx="6.769016" />
<p fId="0" fbTx="6.78" lbTx="6.780336" tId="1" fbRx="6.782" lbRx="6.782336" />
<p fId="1" fbTx="6.782336" lbTx="6.784016" tId="2" fbRx="6.787336" lbRx="6.789016" />
<p fId="0" fbTx="6.8" lbTx="6.800336" tId="1" fbRx="6.802" lbRx="6.802336" />
<p fId="1" fbTx="6.802336" lbTx="6.804016" tId="2" fbRx="6.807336" lbRx="6.809016" />
<p fId="0" fbTx="6.82" lbTx="6.820336" tId="1" fbRx="6.822" lbRx="6.822336" />
<p fId="1" fbTx="6.822336" lbTx="6.824016" tId="2" fbRx="6.827336" lbRx="6.829016" />
<p fId="0" fbTx="6.84" lbTx="6.840336" tId="1" fbRx="6.842" lbRx="6.842336" />
<p fId="1" fbTx="6.842336" lbTx="6.844016" tId="2" fbRx="6.847336" lbRx="6.849016" />
<p fId="0" fbTx="6.86" lbTx="6.860336" tId="1" fbRx="6.862" lbRx="6.862336" />
<p fId="1" fbTx="6.862336" lbTx="6.864016" tId="2" fbRx="6.867336" lbRx="6.869016" />
<p fId="0" fbTx="6.88" lbTx="6.880336" tId="1" fbRx="6.882" lbRx="6.882336" />
<p fId="1" fbTx="6.882336" lbTx="6.884016" tId="2" fbRx="6.887336" lbRx="6.889016" />
<p fId="0" fbTx="6.9" lbTx="6.900336" tId="1" fbRx="6.902" lbRx="6.902336" />
<p fId="1" fbTx="6.902336" lbTx="6.904016" tId="2" fbRx="6.907336" lbRx="6.909016" />
<p fId="0" fbTx="6.92" lbTx="6.920336" tId="1" fbRx="6.922" lbRx="6.922336" />
<p fId="1" fbTx="6.922336" lbTx="6.924016" tId="2" fbRx="6.927336" lbRx="6.929016" />
<p fId="0" fbTx="6.94" lbTx="6.940336" tId="1" fbRx="6.942" lbRx="6.942336" />
<p fId="1" fbTx="6.942336" lbTx="6.944016" tId="2" fbRx="6.947336" lbRx="6.949016" />
<p fId="0" fbTx="6.96" lbTx="6.960336" tId="1" fbRx="6.962" lbRx="6.962336" />
<p fId="1" fbTx="6.962336" lbTx="6.964016" tId="2" fbRx="6.967336" lbRx="6.969016" />
<p fId="0" fbTx="6.98" lbTx="6.980336" tId="1" fbRx="6.982" lbRx="6.982336" />
<p fId="1" fbTx="6.982336" lbTx="6.984016" tId="2" fbRx="6.987336" lbRx="6.989016" />
<p fId="0" fbTx="7" lbTx="7.000336" tId="1" fbRx="7.002" lbRx="7.002336" />
<p fId="1" fbTx="7.002336" lbTx="7.004016" tId="2" fbRx="7.007336" lbRx="7.009016" />
<p fId="0" fbTx="7.02" lbTx="7.020336" tId="1" fbRx="7.022" lbRx="7.022336" />
<p fId="1" fbTx="7.022336" lbTx="7.024016" tId="2" fbRx="7.027336" lbRx="7.029016" />
<p fId="0" fbTx="7.04" lbTx="7.040336" tId="1" fbRx="7.042" lbRx="7.042336" />
<p fId="1" fbTx="7.042336" lbTx="7.044016" tId="2" fbRx="7.047336" lbRx="7.049016" />
<p fId="0" fbTx="7.06" lbTx="7.060336" tId="1" fbRx="7.062" lbRx="7.062336" />
<p fId="1" fbTx="7.062336" lbTx="7.064016" tId="2" fbRx="7.067336" lbRx="7.069016" />
<p fId="0" fbTx="7.08" lbTx="7.080336" tId="1" fbRx="7.082" lbRx="7.082336" />
<p fId="1" fbTx="7.082336" lbTx="7.084016" tId="2" fbRx="7.087336" lbRx="7.089016" />
<p fId="0" fbTx="7.1" lbTx="7.100336" tId="1" fbRx="7.102" lbRx="7.102336" />
<p fId="1" fbTx="7.102336" lbTx="7.104016" tId="2" fbRx="7.107336" lbRx="7.109016" />
<p fId="0" fbTx="7.12" lbTx="7.120336" tId="1" fbRx="7.122" lbRx="7.122336" />
<p fId="1" fbTx="7.122336" lbTx="7.124016" tId="2" fbRx="7.127336" lbRx="7.129016" />
<p fId="0" fbTx="7.14" lbTx="7.140336" tId="1" fbRx="7.142" lbRx="7.142336" />
<p fId="1" fbTx="7.142336" lbTx="7.144016" tId="2" fbRx="7.147336" lbRx="7.149016" />
<p fId="0" fbTx="7.16" lbTx="7.160336" tId="1" fbRx="7.162" lbRx="7.162336" />
<p fId="1" fbTx="7.162336" lbTx="7.164016" tId="2" fbRx="7.167336" lbRx="7.169016" />
<p fId="0" fbTx="7.18" lbTx="7.180336" tId="1" fbRx="7.182" lbRx="7.182336" />
<p fId="1" fbTx="7.182336" lbTx="7.184016" tId="2" fbRx="7.187336" lbRx="7.189016" />
<p fId="0" fbTx="7.2" lbTx="7.200336" tId="1" fbRx="7.202" lbRx="7.202336" />
<p fId="1" fbTx="7.202336" lbTx="7.204016" tId="2" fbRx="7.207336" lbRx="7.209016" />
<p fId="0" fbTx="7.22" lbTx="7.220336" tId="1" fbRx="7.222" lbRx="7.222336" />
<p fId="1" fbTx="7.222336" lbTx="7.224016" tId="2" fbRx="7.227336" lbRx="7.229016" />
<p fId="0" fbTx="7.24" lbTx="7.240336" tId="1" fbRx="7.242" lbRx="7.242336" />
<p fId="1" fbTx="7.242336" lbTx="7.244016" tId="2" fbRx="7.247336" lbRx="7.249016" />
<p fId="0" fbTx="7.26" lbTx="7.260336" tId="1" fbRx="7.262" lbRx="7.262336" />
<p fId="1" fbTx="7.262336" lbTx="7.264016" tId="2" fbRx="7.267336" lbRx="7.269016" />
<p fId="0" fbTx="7.28" lbTx="7.280336" tId="1" fbRx="7.282" lbRx="7.282336" />
<p fId="1" fbTx="7.282336" lbTx="7.284016" tId="2" fbRx="7.287336" lbRx="7.289016" />
<p fId="0" fbTx="7.3" lbTx="7.300336" tId="1" fbRx="7.302" lbRx="7.302336" />
<p fId="1" fbTx="7.302336" lbTx="7.304016" tId="2" fbRx="7.307336" lbRx="7.309016" />
<p fId="0" fbTx="7.32" lbTx="7.320336" tId="1" fbRx="7.322" lbRx="7.322336" />
<p fId="1" fbTx="7.322336" lbTx="7.324016" tId="2" fbRx="7.327336" lbRx="7.329016" />
<p fId="0" fbTx="7.34" lbTx="7.340336" tId="1" fbRx="7.342" lbRx="7.342336" />
<p fId="1" fbTx="7.342336" lbTx="7.344016" tId="2" fbRx="7.347336" lbRx="7.349016" />
<p fId="0" fbTx="7.36" lbTx="7.360336" tId="1" fbRx="7.362" lbRx="7.362336" />
<p fId="1" fbTx="7.362336" lbTx="7.364016" tId="2" fbRx="7.367336" lbRx="7.369016" />
<p fId="0" fbTx="7.38" lbTx="7.380336" tId="1" fbRx="7.382" lbRx="7.382336" />
<p fId="1" fbTx="7.382336" lbTx="7.384016" tId="2" fbRx="7.387336" lbRx="7.389016" />
<p fId="0" fbTx="7.4" lbTx="7.400336" tId="1" fbRx="7.402" lbRx="7.402336" />
<p fId="1" fbTx="7.402336" lbTx="7.404016" tId="2" fbRx="7.407336" lbRx="7.409016" />
<p fId="0" fbTx="7.42" lbTx="7.420336" tId="1" fbRx="7.422" lbRx="7.422336" />
<p fId="1" fbTx="7.422336" lbTx="7.424016" tId="2" fbRx="7.427336" lbRx="7.429016" />
<p fId="0" fbTx="7.44" lbTx="7.440336" tId="1" fbRx="7.442" lbRx="7.442336" />
<p fId="1" fbTx="7.442336" lbTx="7.444016" tId="2" fbRx="7.447336" lbRx="7.449016" />
<p fId="0" fbTx="7.46" lbTx="7.460336" tId="1" fbRx="7.462" lbRx="7.462336" />
<p fId="1" fbTx="7.462336" lbTx="7.464016" tId="2" fbRx="7.467336" lbRx="7.469016" />
<p fId="0" fbTx="7.48" lbTx="7.480336" tId="1" fbRx="7.482" lbRx="7.482336" />
<p fId="1" fbTx="7.482336" lbTx="7.484016" tId="2" fbRx="7.487336" lbRx="7.489016" />
<p fId="0" fbTx="7.5" lbTx="7.500336" tId="1" fbRx="7.502" lbRx="7.502336" />
<p fId="1" fbTx="7.502336" lbTx="7.504016" tId="2" fbRx="7.507336" lbRx="7.509016" />
<p fId="0" fbTx="7.52" lbTx="7.520336" tId="1" fbRx="7.522" lbRx="7.522336" />
<p fId="1" fbTx="7.522336" lbTx="7.524016" tId="2" fbRx="7.527336" lbRx="7.529016" />
<p fId="0" fbTx="7.54" lbTx="7.540336" tId="1" fbRx="7.542" lbRx="7.542336" />
<p fId="1" fbTx="7.542336" lbTx="7.544016" tId="2" fbRx="7.547336" lbRx="7.549016" />
<p fId="0" fbTx="7.56" lbTx="7.560336" tId="1" fbRx="7.562" lbRx="7.562336" />
<p fId="1" fbTx="7.562336" lbTx="7.564016" tId="2" fbRx="7.567336" lbRx="7.569016" />
<p fId="0" fbTx="7.58" lbTx="7.580336" tId="1" fbRx="7.582" lbRx="7.582336" />
<p fId="1" fbTx="7.582336" lbTx="7.584016" tId="2" fbRx="7.587336" lbRx="7.589016" />
<p fId="0" fbTx="7.6" lbTx="7.600336" tId="1" fbRx="7.602" lbRx="7.602336" />
<p fId="1" fbTx="7.602336" lbTx="7.604016" tId="2" fbRx="7.607336" lbRx="7.609016" />
<p fId="0" fbTx="7.62" lbTx="7.620336" tId="1" fbRx="7.622" lbRx="7.622336" />
<p fId="1" fbTx="7.622336" lbTx="7.624016" tId="2" fbRx="7.627336" lbRx="7.629016" />
<p fId="0" fbTx="7.64" lbTx="7.640336" tId="1" fbRx="7.642" lbRx="7.642336" />
<p fId="1" fbTx="7.642336" lbTx="7.644016" tId="2" fbRx="7.647336" lbRx="7.649016" />
<p fId="0" fbTx="7.66" lbTx="7.660336" tId="1" fbRx="7.662" lbRx="7.662336" />
<p fId="1" fbTx="7.662336" lbTx="7.664016" tId="2" fbRx="7.667336" lbRx="7.669016" />
<p fId="0" fbTx="7.68" lbTx="7.680336" tId="1" fbRx="7.682" lbRx="7.682336" />
<p fId="1" fbTx="7.682336" lbTx="7.684016" tId="2" fbRx="7.687336" lbRx="7.689016" />
<p fId="0" fbTx="7.7" lbTx="7.700336" tId="1" fbRx="7.702" lbRx="7.702336" />
<p fId="1" fbTx="7.702336" lbTx="7.704016" tId="2" fbRx="7.707336" lbRx="7.709016" />
<p fId="0" fbTx="7.72" lbTx="7.720336" tId="1" fbRx="7.722" lbRx="7.722336" />
<p fId="1" fbTx="7.722336" lbTx="7.724016" tId="2" fbRx="7.727336" lbRx="7.729016" />
<p fId="0" fbTx="7.74" lbTx="7.740336" tId="1" fbRx="7.742" lbRx="7.742336" />
<p fId="1" fbTx="7.742336" lbTx="7.744016" tId="2" fbRx="7.747336" lbRx="7.749016" />
<p fId="0" fbTx="7.76" lbTx="7.760336" tId="1" fbRx="7.762" lbRx="7.762336" />
<p fId="1" fbTx="7.762336" lbTx="7.764016" tId="2" fbRx="7.767336" lbRx="7.769016" />
<p fId="0" fbTx="7.78" lbTx="7.780336" tId="1" fbRx="7.782" lbRx="7.782336" />
<p fId="1" fbTx="7.782336" lbTx="7.784016" tId="2" fbRx="7.787336" lbRx="7.789016" />
<p fId="0" fbTx="7.8" lbTx="7.800336" tId="1" fbRx="7.802" lbRx="7.802336" />
<p fId="1" fbTx="7.802336" lbTx="7.804016" tId="2" fbRx="7.807336" lbRx="7.809016" />
<p fId="0" fbTx="7.82" lbTx="7.820336" tId="1" fbRx="7.822" lbRx="7.822336" />
<p fId="1" fbTx="7.822336" lbTx="7.824016" tId="2" fbRx="7.827336" lbRx="7.829016" />
<p fId="0" fbTx="7.84" lbTx="7.840336" tId="1" fbRx="7.842" lbRx="7.842336" />
<p fId="1" fbTx="7.842336" lbTx="7.844016" tId="2" fbRx="7.847336" lbRx="7.849016" />
<p fId="0" fbTx="7.86" lbTx="7.860336" tId="1" fbRx="7.862" lbRx="7.862336" />
<p fId="1" fbTx="7.862336" lbTx="7.864016" tId="2" fbRx="7.867336" lbRx="7.869016" />
<p fId="0" fbTx="7.88" lbTx="7.880336" tId="1" fbRx="7.882" lbRx="7.882336" />
<p fId="1" fbTx="7.882336" lbTx="7.884016" tId="2" fbRx="7.887336" lbRx="7.889016" />
<p fId="0" fbTx="7.9" lbTx="7.900336" tId="1" fbRx="7.902" lbRx="7.902336" />
<p fId="1" fbTx="7.902336" lbTx="7.904016" tId="2" fbRx="7.907336" lbRx="7.909016" />
<p fId="0" fbTx="7.92" lbTx="7.920336" tId="1" fbRx="7.922" lbRx="7.922336" />
<p fId="1" fbTx="7.922336" lbTx="7.924016" tId="2" fbRx="7.927336" lbRx="7.929016" />
<p fId="0" fbTx="7.94" lbTx="7.940336" tId="1" fbRx="7.942" lbRx="7.942336" />
<p fId="1" fbTx="7.942336" lbTx="7.944016" tId="2" fbRx="7.947336" lbRx="7.949016" />
<p fId="0" fbTx="7.96" lbTx="7.960336" tId="1" fbRx="7.962" lbRx="7.962336" />
<p fId="1" fbTx="7.962336" lbTx="7.964016" tId="2" fbRx="7.967336" lbRx="7.969016" />
<p fId="0" fbTx="7.98" lbTx="7.980336" tId="1" fbRx="7.982" lbRx="7.982336" />
<p fId="1" fbTx="7.982336" lbTx="7.984016" tId="2" fbRx="7.987336" lbRx="7.989016" />
<p fId="0" fbTx="8" lbTx="8.000336" tId="1" fbRx="8.002" lbRx="8.002336" />
<p fId="1" fbTx="8.002336" lbTx="8.004016" tId="2" fbRx="8.007336" lbRx="8.009016" />
<p fId="0" fbTx="8.02" lbTx="8.020336" tId="1" fbRx="8.022" lbRx="8.022336" />
<p fId="1" fbTx="8.022336" lbTx="8.024016" tId="2" fbRx="8.027336" lbRx="8.029016" />
<p fId="0" fbTx="8.04" lbTx="8.040336" tId="1" fbRx="8.042" lbRx="8.042336" />
<p fId="1" fbTx="8.042336" lbTx="8.044016" tId="2" fbRx="8.047336" lbRx="8.049016" />
<p fId="0" fbTx="8.06" lbTx="8.060336" tId="1" fbRx="8.062" lbRx="8.062336" />
<p fId="1" fbTx="8.062336" lbTx="8.064016" tId="2" fbRx="8.067336" lbRx="8.069016" />
<p fId="0" fbTx="8.08" lbTx="8.080336" tId="1" fbRx="8.082" lbRx="8.082336" />
<p fId="1" fbTx="8.082336" lbTx="8.084016" tId="2" fbRx="8.087336" lbRx="8.089016" />
<p fId="0" fbTx="8.1" lbTx="8.100336" tId="1" fbRx="8.102" lbRx="8.102336" />
<p fId="1" fbTx="8.102336" lbTx="8.104016" tId="2" fbRx="8.107336" lbRx="8.109016" />
<p fId="0" fbTx="8.12" lbTx="8.120336" tId="1" fbRx="8.122" lbRx="8.122336" />
<p fId="1" fbTx="8.122336" lbTx="8.124016" tId="2" fbRx="8.127336" lbRx="8.129016" />
<p fId="0" fbTx="8.14" lbTx="8.140336" tId="1" fbRx="8.142" lbRx="8.142336" />
<p fId="1" fbTx="8.142336" lbTx="8.144016" tId="2" fbRx="8.147336" lbRx="8.149016" />
<p fId="0" fbTx="8.16" lbTx="8.160336" tId="1" fbRx="8.162" lbRx="8.162336" />
<p fId="1" fbTx="8.162336" lbTx="8.164016" tId="2" fbRx="8.167336" lbRx="8.169016" />
<p fId="0" fbTx="8.18" lbTx="8.180336" tId="1" fbRx="8.182" lbRx="8.182336" />
<p fId="1" fbTx="8.182336" lbTx="8.184016" tId="2" fbRx="8.187336" lbRx="8.189016" />
<p fId="0" fbTx="8.2" lbTx="8.200336" tId="1" fbRx="8.202" lbRx="8.202336" />
<p fId="1" fbTx="8.202336" lbTx="8.204016" tId="2" fbRx="8.207336" lbRx="8.209016" />
<p fId="0" fbTx="8.22" lbTx="8.220336" tId="1" fbRx="8.222" lbRx="8.222336" />
<p fId="1" fbTx="8.222336" lbTx="8.224016" tId="2" fbRx="8.227336" lbRx="8.229016" />
<p fId="0" fbTx="8.24" lbTx="8.240336" tId="1" fbRx="8.242" lbRx="8.242336" />
<p fId="1" fbTx="8.242336" lbTx="8.244016" tId="2" fbRx="8.247336" lbRx="8.249016" />
<p fId="0" fbTx="8.26" lbTx="8.260336" tId="1" fbRx="8.262" lbRx="8.262336" />
<p fId="1" fbTx="8.262336" lbTx="8.264016" tId="2" fbRx="8.267336" lbRx="8.269016" />
<p fId="0" fbTx="8.28" lbTx="8.280336" tId="1" fbRx="8.282" lbRx="8.282336" />
<p fId="1" fbTx="8.282336" lbTx="8.284016" tId="2" fbRx="8.287336" lbRx="8.289016" />
<p fId="0" fbTx="8.3" lbTx="8.300336" tId="1" fbRx="8.302" lbRx="8.302336" />
<p fId="1" fbTx="8.302336" lbTx="8.304016" tId="2" fbRx="8.307336" lbRx="8.309016" />
<p fId="0" fbTx="8.32" lbTx="8.320336" tId="1" fbRx="8.322" lbRx="8.322336" />
<p fId="1" fbTx="8.322336" lbTx="8.324016" tId="2" fbRx="8.327336" lbRx="8.329016" />
<p fId="0" fbTx="8.34" lbTx="8.340336" tId="1" fbRx="8.342" lbRx="8.342336" />
<p fId="1" fbTx="8.342336" lbTx="8.344016" tId="2" fbRx="8.347336" lbRx="8.349016" />
<p fId="0" fbTx="8.36" lbTx="8.360336" tId="1" fbRx="8.362" lbRx="8.362336" />
<p fId="1" fbTx="8.362336" lbTx="8.364016" tId="2" fbRx="8.367336" lbRx="8.369016" />
<p fId="0" fbTx="8.38" lbTx="8.380336" tId="1" fbRx="8.382" lbRx="8.382336" />
<p fId="1" fbTx="8.382336" lbTx="8.384016" tId="2" fbRx="8.387336" lbRx="8.389016" />
<p fId="0" fbTx="8.4" lbTx="8.400336" tId="1" fbRx="8.402" lbRx="8.402336" />
<p fId="1" fbTx="8.402336" lbTx="8.404016" tId="2" fbRx="8.407336" lbRx="8.409016" />
<p fId="0" fbTx="8.42" lbTx="8.420336" tId="1" fbRx="8.422" lbRx="8.422336" />
<p fId="1" fbTx="8.422336" lbTx="8.424016" tId="2" fbRx="8.427336" lbRx="8.429016" />
<p fId="0" fbTx="8.44" lbTx="8.440336" tId="1" fbRx="8.442" lbRx="8.442336" />
<p fId="1" fbTx="8.442336" lbTx="8.444016" tId="2" fbRx="8.447336" lbRx="8.449016" />
<p fId="0" fbTx="8.46" lbTx="8.460336" tId="1" fbRx="8.462" lbRx="8.462336" />
<p fId="1" fbTx="8.462336" lbTx="8.464016" tId="2" fbRx="8.467336" lbRx="8.469016" />
<p fId="0" fbTx="8.48" lbTx="8.480336" tId="1" fbRx="8.482" lbRx="8.482336" />
<p fId="1" fbTx="8.482336" lbTx="8.484016" tId="2" fbRx="8.487336" lbRx="8.489016" />
<p fId="0" fbTx="8.5" lbTx="8.500336" tId="1" fbRx="8.502" lbRx="8.502336" />
<p fId="1" fbTx="8.502336" lbTx="8.504016" tId="2" fbRx="8.507336" lbRx="8.509016" />
<p fId="0" fbTx="8.52" lbTx="8.520336" tId="1" fbRx="8.522" lbRx="8.522336" />
<p fId="1" fbTx="8.522336" lbTx="8.524016" tId="2" fbRx="8.527336" lbRx="8.529016" />
<p fId="0" fbTx="8.54" lbTx="8.540336" tId="1" fbRx="8.542" lbRx="8.542336" />
<p fId="1" fbTx="8.542336" lbTx="8.544016" tId="2" fbRx="8.547336" lbRx="8.549016" />
<p fId="0" fbTx="8.56" lbTx="8.560336" tId="1" fbRx="8.562" lbRx="8.562336" />
<p fId="1" fbTx="8.562336" lbTx="8.564016" tId="2" fbRx="8.567336" lbRx="8.569016" />
<p fId="0" fbTx="8.58" lbTx="8.580336" tId="1" fbRx="8.582" lbRx="8.582336" />
<p fId="1" fbTx="8.582336" lbTx="8.584016" tId="2" fbRx="8.587336" lbRx="8.589016" />
<p fId="0" fbTx="8.6" lbTx="8.600336" tId="1" fbRx="8.602" lbRx="8.602336" />
<p fId="1" fbTx="8.602336" lbTx="8.604016" tId="2" fbRx="8.607336" lbRx="8.609016" />
<p fId="0" fbTx="8.62" lbTx="8.620336" tId="1" fbRx="8.622" lbRx="8.622336" />
<p fId="1" fbTx="8.622336" lbTx="8.624016" tId="2" fbRx="8.627336" lbRx="8.629016" />
<p fId="0" fbTx="8.64" lbTx="8.640336" tId="1" fbRx="8.642" lbRx="8.642336" />
<p fId="1" fbTx="8.642336" lbTx="8.644016" tId="2" fbRx="8.647336" lbRx="8.649016" />
<p fId="0" fbTx="8.66" lbTx="8.660336" tId="1" fbRx="8.662" lbRx="8.662336" />
<p fId="1" fbTx="8.662336" lbTx="8.664016" tId="2" fbRx="8.667336" lbRx="8.669016" />
<p fId="0" fbTx="8.68" lbTx="8.680336" tId="1" fbRx="8.682" lbRx="8.682336" />
<p fId="1" fbTx="8.682336" lbTx="8.684016" tId="2" fbRx="8.687336" lbRx="8.689016" />
<p fId="0" fbTx="8.7" lbTx="8.700336" tId="1" fbRx="8.702" lbRx="8.702336" />
<p fId="1" fbTx="8.702336" lbTx="8.704016" tId="2" fbRx="8.707336" lbRx="8.709016" />
<p fId="0" fbTx="8.72" lbTx="8.720336" tId="1" fbRx="8.722" lbRx="8.722336" />
<p fId="1" fbTx="8.722336" lbTx="8.724016" tId="2" fbRx="8.727336" lbRx="8.729016" />
<p fId="0" fbTx="8.74" lbTx="8.740336" tId="1" fbRx="8.742" lbRx="8.742336" />
<p fId="1" fbTx="8.742336" lbTx="8.744016" tId="2" fbRx="8.747336" lbRx="8.749016" />
<p fId="0" fbTx="8.76" lbTx="8.760336" tId="1" fbRx="8.762" lbRx="8.762336" />
<p fId="1" fbTx="8.762336" lbTx="8.764016" tId="2" fbRx="8.767336" lbRx="8.769016" />
<p fId="0" fbTx="8.78" lbTx="8.780336" tId="1" fbRx="8.782" lbRx="8.782336" />
<p fId="1" fbTx="8.782336" lbTx="8.784016" tId="2" fbRx="8.787336" lbRx="8.789016" />
<p fId="0" fbTx="8.8" lbTx="8.800336" tId="1" fbRx="8.802" lbRx="8.802336" />
<p fId="1" fbTx="8.802336" lbTx="8.804016" tId="2" fbRx="8.807336" lbRx="8.809016" />
<p fId="0" fbTx="8.82" lbTx="8.820336" tId="1" fbRx="8.822" lbRx="8.822336" />
<p fId="1" fbTx="8.822336" lbTx="8.824016" tId="2" fbRx="8.827336" lbRx="8.829016" />
<p fId="0" fbTx="8.84" lbTx="8.840336" tId="1" fbRx="8.842" lbRx="8.842336" />
<p fId="1" fbTx="8.842336" lbTx="8.844016" tId="2" fbRx="8.847336" lbRx="8.849016" />
<p fId="0" fbTx="8.86" lbTx="8.860336" tId="1" fbRx="8.862" lbRx="8.862336" />
<p fId="1" fbTx="8.862336" lbTx="8.864016" tId="2" fbRx="8.867336" lbRx="8.869016" />
<p fId="0" fbTx="8.88" lbTx="8.880336" tId="1" fbRx="8.882" lbRx="8.882336" />
<p fId="1" fbTx="8.882336" lbTx="8.884016" tId="2" fbRx="8.887336" lbRx="8.889016" />
<p fId="0" fbTx="8.9" lbTx="8.900336" tId="1" fbRx="8.902" lbRx="8.902336" />
<p fId="1" fbTx="8.902336" lbTx="8.904016" tId="2" fbRx="8.907336" lbRx="8.909016" />
<p fId="0" fbTx="8.92" lbTx="8.920336" tId="1" fbRx="8.922" lbRx="8.922336" />
<p fId="1" fbTx="8.922336" lbTx="8.924016" tId="2" fbRx="8.927336" lbRx="8.929016" />
<p fId="0" fbTx="8.94" lbTx="8.940336" tId="1" fbRx="8.942" lbRx="8.942336" />
<p fId="1" fbTx="8.942336" lbTx="8.944016" tId="2" fbRx="8.947336" lbRx="8.949016" />
<p fId="0" fbTx="8.96" lbTx="8.960336" tId="1" fbRx="8.962" lbRx="8.962336" />
<p fId="1" fbTx="8.962336" lbTx="8.964016" tId="2" fbRx="8.967336" lbRx="8.969016" />
<p fId="0" fbTx="8.98" lbTx="8.980336" tId="1" fbRx="8.982" lbRx="8.982336" />
<p fId="1" fbTx="8.982336" lbTx="8.984016" tId="2" fbRx="8.987336" lbRx="8.989016" />
<p fId="0" fbTx="9" lbTx="9.000336" tId="1" fbRx="9.002" lbRx="9.002336" />
<p fId="1" fbTx="9.002336" lbTx="9.004016" tId="2" fbRx="9.007336" lbRx="9.009016" />
<p fId="0" fbTx="9.02" lbTx="9.020336" tId="1" fbRx="9.022" lbRx="9.022336" />
<p fId="1" fbTx="9.022336" lbTx="9.024016" tId="2" fbRx="9.027336" lbRx="9.029016" />
<p fId="0" fbTx="9.04" lbTx="9.040336" tId="1" fbRx="9.042" lbRx="9.042336" />
<p fId="1" fbTx="9.042336" lbTx="9.044016" tId="2" fbRx="9.047336" lbRx="9.049016" />
<p fId="0" fbTx="9.06" lbTx="9.060336" tId="1" fbRx="9.062" lbRx="9.062336" />
<p fId="1" fbTx="9.062336" lbTx="9.064016" tId="2" fbRx="9.067336" lbRx="9.069016" />
<p fId="0" fbTx="9.08" lbTx="9.080336" tId="1" fbRx="9.082" lbRx="9.082336" />
<p fId="1" fbTx="9.082336" lbTx="9.084016" tId="2" fbRx="9.087336" lbRx="9.089016" />
<p fId="0" fbTx="9.1" lbTx="9.100336" tId="1" fbRx="9.102" lbRx="9.102336" />
<p fId="1" fbTx="9.102336" lbTx="9.104016" tId="2" fbRx="9.107336" lbRx="9.109016" />
<p fId="0" fbTx="9.12" lbTx="9.120336" tId="1" fbRx="9.122" lbRx="9.122336" />
<p fId="1" fbTx="9.122336" lbTx="9.124016" tId="2" fbRx="9.127336" lbRx="9.129016" />
<p fId="0" fbTx="9.14" lbTx="9.140336" tId="1" fbRx="9.142" lbRx="9.142336" />
<p fId="1" fbTx="9.142336" lbTx="9.144016" tId="2" fbRx="9.147336" lbRx="9.149016" />
<p fId="0" fbTx="9.16" lbTx="9.160336" tId="1" fbRx="9.162" lbRx="9.162336" />
<p fId="1" fbTx="9.162336" lbTx="9.164016" tId="2" fbRx="9.167336" lbRx="9.169016" />
<p fId="0" fbTx="9.18" lbTx="9.180336" tId="1" fbRx="9.182" lbRx="9.182336" />
<p fId="1" fbTx="9.182336" lbTx="9.184016" tId="2" fbRx="9.187336" lbRx="9.189016" />
<p fId="0" fbTx="9.2" lbTx="9.200336" tId="1" fbRx="9.202" lbRx="9.202336" />
<p fId="1" fbTx="9.202336" lbTx="9.204016" tId="2" fbRx="9.207336" lbRx="9.209016" />
<p fId="0" fbTx="9.22" lbTx="9.220336" tId="1" fbRx="9.222" lbRx="9.222336" />
<p fId="1" fbTx="9.222336" lbTx="9.224016" tId="2" fbRx="9.227336" lbRx="9.229016" />
<p fId="0" fbTx="9.24" lbTx="9.240336" tId="1" fbRx="9.242" lbRx="9.242336" />
<p fId="1" fbTx="9.242336" lbTx="9.244016" tId="2" fbRx="9.247336" lbRx="9.249016" />
<p fId="0" fbTx="9.26" lbTx="9.260336" tId="1" fbRx="9.262" lbRx="9.262336" />
<p fId="1" fbTx="9.262336" lbTx="9.264016" tId="2" fbRx="9.267336" lbRx="9.269016" />
<p fId="0" fbTx="9.28" lbTx="9.280336" tId="1" fbRx="9.282" lbRx="9.282336" />
<p fId="1" fbTx="9.282336" lbTx="9.284016" tId="2" fbRx="9.287336" lbRx="9.289016" />
<p fId="0" fbTx="9.3" lbTx="9.300336" tId="1" fbRx="9.302" lbRx="9.302336" />
<p fId="1" fbTx="9.302336" lbTx="9.304016" tId="2" fbRx="9.307336" lbRx="9.309016" />
<p fId="0" fbTx="9.32" lbTx="9.320336" tId="1" fbRx="9.322" lbRx="9.322336" />
<p fId="1" fbTx="9.322336" lbTx="9.324016" tId="2" fbRx="9.327336" lbRx="9.329016" />
<p fId="0" fbTx="9.34" lbTx="9.340336" tId="1" fbRx="9.342" lbRx="9.342336" />
<p fId="1" fbTx="9.342336" lbTx="9.344016" tId="2" fbRx="9.347336" lbRx="9.349016" />
<p fId="0" fbTx="9.36" lbTx="9.360336" tId="1" fbRx="9.362" lbRx="9.362336" />
<p fId="1" fbTx="9.362336" lbTx="9.364016" tId="2" fbRx="9.367336" lbRx="9.369016" />
<p fId="0" fbTx="9.38" lbTx="9.380336" tId="1" fbRx="9.382" lbRx="9.382336" />
<p fId="1" fbTx="9.382336" lbTx="9.384016" tId="2" fbRx="9.387336" lbRx="9.389016" />
<p fId="0" fbTx="9.4" lbTx="9.400336" tId="1" fbRx="9.402" lbRx="9.402336" />
<p fId="1" fbTx="9.402336" lbTx="9.404016" tId="2" fbRx="9.407336" lbRx="9.409016" />
<p fId="0" fbTx="9.42" lbTx="9.420336" tId="1" fbRx="9.422" lbRx="9.422336" />
<p fId="1" fbTx="9.422336" lbTx="9.424016" tId="2" fbRx="9.427336" lbRx="9.429016" />
<p fId="0" fbTx="9.44" lbTx="9.440336" tId="1" fbRx="9.442" lbRx="9.442336" />
<p fId="1" fbTx="9.442336" lbTx="9.444016" tId="2" fbRx="9.447336" lbRx="9.449016" />
<p fId="0" fbTx="9.46" lbTx="9.460336" tId="1" fbRx="9.462" lbRx="9.462336" />
<p fId="1" fbTx="9.462336" lbTx="9.464016" tId="2" fbRx="9.467336" lbRx="9.469016" />
<p fId="0" fbTx="9.48" lbTx="9.480336" tId="1" fbRx="9.482" lbRx="9.482336" />
<p fId="1" fbTx="9.482336" lbTx="9.484016" tId="2" fbRx="9.487336" lbRx="9.489016" />
<p fId="0" fbTx="9.5" lbTx="9.500336" tId="1" fbRx="9.502" lbRx="9.502336" />
<p fId="1" fbTx="9.502336" lbTx="9.504016" tId="2" fbRx="9.507336" lbRx="9.509016" />
<p fId="0" fbTx="9.52" lbTx="9.520336" tId="1" fbRx="9.522" lbRx="9.522336" />
<p fId="1" fbTx="9.522336" lbTx="9.524016" tId="2" fbRx="9.527336" lbRx="9.529016" />
<p fId="0" fbTx="9.54" lbTx="9.540336" tId="1" fbRx="9.542" lbRx="9.542336" />
<p fId="1" fbTx="9.542336" lbTx="9.544016" tId="2" fbRx="9.547336" lbRx="9.549016" />
<p fId="0" fbTx="9.56" lbTx="9.560336" tId="1" fbRx="9.562" lbRx="9.562336" />
<p fId="1" fbTx="9.562336" lbTx="9.564016" tId="2" fbRx="9.567336" lbRx="9.569016" />
<p fId="0" fbTx="9.58" lbTx="9.580336" tId="1" fbRx="9.582" lbRx="9.582336" />
<p fId="1" fbTx="9.582336" lbTx="9.584016" tId="2" fbRx="9.587336" lbRx="9.589016" />
<p fId="0" fbTx="9.6" lbTx="9.600336" tId="1" fbRx="9.602" lbRx="9.602336" />
<p fId="1" fbTx="9.602336" lbTx="9.604016" tId="2" fbRx="9.607336" lbRx="9.609016" />
<p fId="0" fbTx="9.62" lbTx="9.620336" tId="1" fbRx="9.622" lbRx="9.622336" />
<p fId="1" fbTx="9.622336" lbTx="9.624016" tId="2" fbRx="9.627336" lbRx="9.629016" />
<p fId="0" fbTx="9.64" lbTx="9.640336" tId="1" fbRx="9.642" lbRx="9.642336" />
<p fId="1" fbTx="9.642336" lbTx="9.644016" tId="2" fbRx="9.647336" lbRx="9.649016" />
<p fId="0" fbTx="9.66" lbTx="9.660336" tId="1" fbRx="9.662" lbRx="9.662336" />
<p fId="1" fbTx="9.662336" lbTx="9.664016" tId="2" fbRx="9.667336" lbRx="9.669016" />
<p fId="0" fbTx="9.68" lbTx="9.680336" tId="1" fbRx="9.682" lbRx="9.682336" />
<p fId="1" fbTx="9.682336" lbTx="9.684016" tId="2" fbRx="9.687336" lbRx="9.689016" />
<p fId="0" fbTx="9.7" lbTx="9.700336" tId="1" fbRx="9.702" lbRx="9.702336" />
<p fId="1" fbTx="9.702336" lbTx="9.704016" tId="2" fbRx="9.707336" lbRx="9.709016" />
<p fId="0" fbTx="9.72" lbTx="9.720336" tId="1" fbRx="9.722" lbRx="9.722336" />
<p fId="1" fbTx="9.722336" lbTx="9.724016" tId="2" fbRx="9.727336" lbRx="9.729016" />
<p fId="0" fbTx="9.74" lbTx="9.740336" tId="1" fbRx="9.742" lbRx="9.742336" />
<p fId="1" fbTx="9.742336" lbTx="9.744016" tId="2" fbRx="9.747336" lbRx="9.749016" />
<p fId="0" fbTx="9.76" lbTx="9.760336" tId="1" fbRx="9.762" lbRx="9.762336" />
<p fId="1" fbTx="9.762336" lbTx="9.764016" tId="2" fbRx="9.767336" lbRx="9.769016" />
<p fId="0" fbTx="9.78" lbTx="9.780336" tId="1" fbRx="9.782" lbRx="9.782336" />
<p fId="1" fbTx="9.782336" lbTx="9.784016" tId="2" fbRx="9.787336" lbRx="9.789016" />
<p fId="0" fbTx="9.8" lbTx="9.800336" tId="1" fbRx="9.802" lbRx="9.802336" />
<p fId="1" fbTx="9.802336" lbTx="9.804016" tId="2" fbRx="9.807336" lbRx="9.809016" />
<p fId="0" fbTx="9.82" lbTx="9.820336" tId="1" fbRx="9.822" lbRx="9.822336" />
<p fId="1" fbTx="9.822336" lbTx="9.824016" tId="2" fbRx="9.827336" lbRx="9.829016" />
<p fId="0" fbTx="9.84" lbTx="9.840336" tId="1" fbRx="9.842" lbRx="9.842336" />
<p fId="1" fbTx="9.842336" lbTx="9.844016" tId="2" fbRx="9.847336" lbRx="9.849016" />
<p fId="0" fbTx="9.86" lbTx="9.860336" tId="1" fbRx="9.862" lbRx="9.862336" />
<p fId="1" fbTx="9.862336" lbTx="9.864016" tId="2" fbRx="9.867336" lbRx="9.869016" />
<p fId="0" fbTx="9.88" lbTx="9.880336" tId="1" fbRx="9.882" lbRx="9.882336" />
<p fId="1" fbTx="9.882336" lbTx="9.884016" tId="2" fbRx="9.887336" lbRx="9.889016" />
<p fId="0" fbTx="9.9" lbTx="9.900336" tId="1" fbRx="9.902" lbRx="9.902336" />
<p fId="1" fbTx="9.902336" lbTx="9.904016" tId="2" fbRx="9.907336" lbRx="9.909016" />
<p fId="0" fbTx="9.92" lbTx="9.920336" tId="1" fbRx="9.922" lbRx="9.922336" />
<p fId="1" fbTx="9.922336" lbTx="9.924016" tId="2" fbRx="9.927336" lbRx="9.929016" />
<p fId="0" fbTx="9.94" lbTx="9.940336" tId="1" fbRx="9.942" lbRx="9.942336" />
<p fId="1" fbTx="9.942336" lbTx="9.944016" tId="2" fbRx="9.947336" lbRx="9.949016" />
<p fId="0" fbTx="9.96" lbTx="9.960336" tId="1" fbRx="9.962" lbRx="9.962336" />
<p fId="1" fbTx="9.962336" lbTx="9.964016" tId="2" fbRx="9.967336" lbRx="9.969016" />
<p fId="0" fbTx="9.98" lbTx="9.980336" tId="1" fbRx="9.982" lbRx="9.982336" />
<p fId="1" fbTx="9.982336" lbTx="9.984016" tId="2" fbRx="9.987336" lbRx="9.989016" />
<p fId="0" fbTx="10" lbTx="10.0000864" tId="1" fbRx="10.002" lbRx="10.0020864" />
<p fId="1" fbTx="10.0020864" lbTx="10.0021728" tId="2" fbRx="10.0220864" lbRx="10.0221728" />
</anim>
